[
    {
        "ai_id": 0,
        "children": [
            {
                "ai_id": "1",
                "child_pos_id": "1",
                "drop_item_list": [],
                "enemy_id": "305036",
                "init_hp": 5332,
                "lv": "77",
                "max_hp": 5332,
                "no": "1",
                "params": [
                    {
                        "abilities": [
                            {
                                "ability_id": "101001",
                                "weight": "30"
                            },
                            {
                                "ability_id": "102078",
                                "weight": "40"
                            },
                            {
                                "ability_id": "102061",
                                "weight": "30"
                            }
                        ],
                        "acc": "100",
                        "animation_info": {
                            "assets": {
                                "enemy-105049": "/Content/lang/ab/character/enemy/105049.sajson"
                            },
                            "enemy_status_id": "3050361",
                            "hp_gauge_size": "2",
                            "offset_x": "0",
                            "offset_y": "-28",
                            "path": "105049",
                            "scale": "2.5",
                            "uses_fix_pos": false
                        },
                        "atk": 356,
                        "breed_id": "18",
                        "counters": [],
                        "critical": "3",
                        "def": 93,
                        "def_attributes": [
                            {
                                "attribute_id": "221",
                                "factor": "1"
                            },
                            {
                                "attribute_id": "211",
                                "factor": "1"
                            },
                            {
                                "attribute_id": "222",
                                "factor": "1"
                            },
                            {
                                "attribute_id": "104",
                                "factor": "21"
                            },
                            {
                                "attribute_id": "220",
                                "factor": "1"
                            },
                            {
                                "attribute_id": "219",
                                "factor": "1"
                            },
                            {
                                "attribute_id": "225",
                                "factor": "1"
                            }
                        ],
                        "disp_name": "Gigas",
                        "eva": "70",
                        "exp": 1565,
                        "id": "3050361",
                        "looking": "0",
                        "lv": "77",
                        "matk": 137,
                        "max_hp": 5332,
                        "mdef": 88,
                        "mnd": 67,
                        "no": "1",
                        "size": "3",
                        "spd": "100"
                    }
                ],
                "uid": "201"
            }
        ],
        "deform_animation_info": [],
        "id": "305036",
        "is_sp_enemy": 0
    },
    {
        "ai_id": 0,
        "children": [
            {
                "ai_id": "1",
                "child_pos_id": "1",
                "drop_item_list": [
                    {
                        "item_id": "40000052",
                        "num": "1",
                        "rarity": "2",
                        "type": 51,
                        "uid": 202
                    }
                ],
                "enemy_id": "305035",
                "init_hp": 4250,
                "lv": "77",
                "max_hp": 4250,
                "no": "1",
                "params": [
                    {
                        "abilities": [
                            {
                                "ability_id": "101001",
                                "weight": "50"
                            },
                            {
                                "ability_id": "201006",
                                "weight": "50"
                            }
                        ],
                        "acc": "100",
                        "animation_info": {
                            "assets": {
                                "enemy-105030": "/Content/lang/ab/character/enemy/105030.sajson"
                            },
                            "enemy_status_id": "3050351",
                            "hp_gauge_size": "2",
                            "offset_x": "10",
                            "offset_y": "-28",
                            "path": "105030",
                            "scale": "2",
                            "uses_fix_pos": false
                        },
                        "atk": 283,
                        "breed_id": "10",
                        "counters": [],
                        "critical": "3",
                        "def": 104,
                        "def_attributes": [
                            {
                                "attribute_id": "220",
                                "factor": "1"
                            },
                            {
                                "attribute_id": "219",
                                "factor": "1"
                            },
                            {
                                "attribute_id": "221",
                                "factor": "1"
                            },
                            {
                                "attribute_id": "225",
                                "factor": "1"
                            },
                            {
                                "attribute_id": "211",
                                "factor": "1"
                            },
                            {
                                "attribute_id": "222",
                                "factor": "1"
                            },
                            {
                                "attribute_id": "202",
                                "factor": "1"
                            }
                        ],
                        "disp_name": "Wyvern",
                        "eva": "62",
                        "exp": 1565,
                        "id": "3050351",
                        "looking": "0",
                        "lv": "77",
                        "matk": 258,
                        "max_hp": 4250,
                        "mdef": 102,
                        "mnd": 88,
                        "no": "1",
                        "size": "3",
                        "spd": "100"
                    }
                ],
                "uid": "202"
            }
        ],
        "deform_animation_info": [],
        "id": "305035",
        "is_sp_enemy": 0
    },
    {
        "ai_id": 0,
        "children": [
            {
                "ai_id": "1",
                "child_pos_id": "1",
                "drop_item_list": [],
                "enemy_id": "305033",
                "init_hp": 4488,
                "lv": "77",
                "max_hp": 4488,
                "no": "1",
                "params": [
                    {
                        "abilities": [
                            {
                                "ability_id": "101001",
                                "weight": "70"
                            },
                            {
                                "ability_id": "201071",
                                "weight": "30"
                            }
                        ],
                        "acc": "100",
                        "animation_info": {
                            "assets": {
                                "enemy-105045": "/Content/lang/ab/character/enemy/105045.sajson"
                            },
                            "enemy_status_id": "3050331",
                            "hp_gauge_size": "2",
                            "offset_x": "0",
                            "offset_y": "-50",
                            "path": "105045",
                            "scale": "2",
                            "uses_fix_pos": false
                        },
                        "atk": 310,
                        "breed_id": "14",
                        "counters": [
                            {
                                "ability_id": "103003",
                                "condition_type": "2",
                                "condition_value": "102",
                                "rate": "100"
                            }
                        ],
                        "critical": "3",
                        "def": 110,
                        "def_attributes": [
                            {
                                "attribute_id": "214",
                                "factor": "1"
                            },
                            {
                                "attribute_id": "201",
                                "factor": "1"
                            },
                            {
                                "attribute_id": "220",
                                "factor": "1"
                            },
                            {
                                "attribute_id": "213",
                                "factor": "1"
                            },
                            {
                                "attribute_id": "209",
                                "factor": "1"
                            },
                            {
                                "attribute_id": "205",
                                "factor": "1"
                            },
                            {
                                "attribute_id": "219",
                                "factor": "1"
                            },
                            {
                                "attribute_id": "102",
                                "factor": "1"
                            },
                            {
                                "attribute_id": "215",
                                "factor": "1"
                            },
                            {
                                "attribute_id": "206",
                                "factor": "1"
                            },
                            {
                                "attribute_id": "222",
                                "factor": "1"
                            },
                            {
                                "attribute_id": "103",
                                "factor": "11"
                            },
                            {
                                "attribute_id": "221",
                                "factor": "1"
                            }
                        ],
                        "disp_name": "Motor Trap",
                        "eva": "86",
                        "exp": 1565,
                        "id": "3050331",
                        "looking": "0",
                        "lv": "77",
                        "matk": 251,
                        "max_hp": 4488,
                        "mdef": 105,
                        "mnd": 105,
                        "no": "1",
                        "size": "3",
                        "spd": "100"
                    }
                ],
                "uid": "203"
            }
        ],
        "deform_animation_info": [],
        "id": "305033",
        "is_sp_enemy": 0
    }
]
