{
    "SERVER_TIME": 1439450997, 
    "assets": [
        {
            "assetPath": "/Content/lang/bgm/bgm_m4a/bgm_03_035.json", 
            "bundle": {
                "/Content/lang/bgm/bgm_m4a/bgm_03_035.json": {
                    "hash": "qDn+SNAishI8Y72d9jygeA"
                }
            }
        }, 
        {
            "assetPath": "/Content/lang/bgm/bgm_m4a/bgm_03_007.json", 
            "bundle": {
                "/Content/lang/bgm/bgm_m4a/bgm_03_007.json": {
                    "hash": "wivOKzk1zaKfqrgc5gyXkg"
                }
            }
        }, 
        {
            "assetPath": "/Content/lang/bgm/bgm_m4a/bgm_03_022.json", 
            "bundle": {
                "/Content/lang/bgm/bgm_m4a/bgm_03_022.json": {
                    "hash": "Bif09ycEu+/UpspUO2k6eQ"
                }
            }
        }, 
        {
            "assetPath": "/Content/lang/bgm/bgm_m4a/bgm_03_003.json", 
            "bundle": {
                "/Content/lang/bgm/bgm_m4a/bgm_03_003.json": {
                    "hash": "eaNSWoDh7vJZPP8CVcgr9g"
                }
            }
        }, 
        {
            "assetPath": "/Content/lang/bgm/bgm_m4a/bgm_03_008.m4a", 
            "bundle": {
                "/Content/lang/bgm/bgm_m4a/bgm_03_008.m4a": {
                    "hash": "cSOtSMftMw3Hv/I1w8CC2g"
                }
            }
        }, 
        {
            "assetPath": "/Content/lang/bgm/bgm_m4a/bgm_03_003.m4a", 
            "bundle": {
                "/Content/lang/bgm/bgm_m4a/bgm_03_003.m4a": {
                    "hash": "pfPl23XiJEqISFUh13BHYA"
                }
            }
        }, 
        {
            "assetPath": "/Content/lang/bgm/bgm_m4a/bgm_03_022.m4a", 
            "bundle": {
                "/Content/lang/bgm/bgm_m4a/bgm_03_022.m4a": {
                    "hash": "86galltEiqXl+7XGd2G2mQ"
                }
            }
        }, 
        {
            "assetPath": "/Content/lang/bgm/bgm_m4a/bgm_03_021.json", 
            "bundle": {
                "/Content/lang/bgm/bgm_m4a/bgm_03_021.json": {
                    "hash": "5dIQAOcZSYtMQLfReBWp2A"
                }
            }
        }, 
        {
            "assetPath": "/Content/lang/bgm/bgm_m4a/bgm_03_045.json", 
            "bundle": {
                "/Content/lang/bgm/bgm_m4a/bgm_03_045.json": {
                    "hash": "LHs61VqW9SQtckcDyFpF6Q"
                }
            }
        }, 
        {
            "assetPath": "/Content/lang/bgm/bgm_m4a/bgm_03_045.m4a", 
            "bundle": {
                "/Content/lang/bgm/bgm_m4a/bgm_03_045.m4a": {
                    "hash": "e4T8Mnrcu4AoTUOjNcg6Pg"
                }
            }
        }, 
        {
            "assetPath": "/Content/lang/bgm/bgm_m4a/bgm_03_008.json", 
            "bundle": {
                "/Content/lang/bgm/bgm_m4a/bgm_03_008.json": {
                    "hash": "Tj3ulmoTfiwaKGBuOLsMFg"
                }
            }
        }, 
        {
            "assetPath": "/Content/lang/bgm/bgm_m4a/bgm_03_033.json", 
            "bundle": {
                "/Content/lang/bgm/bgm_m4a/bgm_03_033.json": {
                    "hash": "jVzCk14OD0fJV7YvlsSx8A"
                }
            }
        }, 
        {
            "assetPath": "/Content/lang/bgm/bgm_m4a/bgm_03_035.m4a", 
            "bundle": {
                "/Content/lang/bgm/bgm_m4a/bgm_03_035.m4a": {
                    "hash": "LCfV4aE3QXej7aQGh2UfAQ"
                }
            }
        }, 
        {
            "assetPath": "/Content/lang/bgm/bgm_m4a/bgm_03_033.m4a", 
            "bundle": {
                "/Content/lang/bgm/bgm_m4a/bgm_03_033.m4a": {
                    "hash": "Fxn3qB2tvBexaDtxKlM4PQ"
                }
            }
        }, 
        {
            "assetPath": "/Content/lang/bgm/bgm_m4a/bgm_03_013.json", 
            "bundle": {
                "/Content/lang/bgm/bgm_m4a/bgm_03_013.json": {
                    "hash": "oylH6h01ffTU5Xir0DQs9g"
                }
            }
        }, 
        {
            "assetPath": "/Content/lang/bgm/bgm_m4a/bgm_03_002.m4a", 
            "bundle": {
                "/Content/lang/bgm/bgm_m4a/bgm_03_002.m4a": {
                    "hash": "37Mk7BGIBEHrbWsJX90FBg"
                }
            }
        }, 
        {
            "assetPath": "/Content/lang/bgm/bgm_m4a/bgm_03_002.json", 
            "bundle": {
                "/Content/lang/bgm/bgm_m4a/bgm_03_002.json": {
                    "hash": "jYx0tTvxLSsOXo0YgiZoLw"
                }
            }
        }, 
        {
            "assetPath": "/Content/lang/bgm/bgm_m4a/bgm_03_009.json", 
            "bundle": {
                "/Content/lang/bgm/bgm_m4a/bgm_03_009.json": {
                    "hash": "k1di30EE+xfdT6o0SODfaQ"
                }
            }
        }, 
        {
            "assetPath": "/Content/lang/bgm/bgm_m4a/bgm_03_021.m4a", 
            "bundle": {
                "/Content/lang/bgm/bgm_m4a/bgm_03_021.m4a": {
                    "hash": "mn0QeKAi+heKUAUTAk8jlg"
                }
            }
        }, 
        {
            "assetPath": "/Content/lang/bgm/bgm_m4a/bgm_03_019.json", 
            "bundle": {
                "/Content/lang/bgm/bgm_m4a/bgm_03_019.json": {
                    "hash": "xdMj/wSqaqsIE7pd2GEYtg"
                }
            }
        }, 
        {
            "assetPath": "/Content/lang/bgm/bgm_m4a/bgm_03_009.m4a", 
            "bundle": {
                "/Content/lang/bgm/bgm_m4a/bgm_03_009.m4a": {
                    "hash": "Sc9mFZqoeYPrK9v7lSGJmg"
                }
            }
        }, 
        {
            "assetPath": "/Content/lang/bgm/bgm_m4a/bgm_03_007.m4a", 
            "bundle": {
                "/Content/lang/bgm/bgm_m4a/bgm_03_007.m4a": {
                    "hash": "t+35rGmSTRFExWVkkfcO5A"
                }
            }
        }, 
        {
            "assetPath": "/Content/lang/bgm/bgm_m4a/bgm_03_013.m4a", 
            "bundle": {
                "/Content/lang/bgm/bgm_m4a/bgm_03_013.m4a": {
                    "hash": "yZghdF2pbhL3SJuB8GRTcA"
                }
            }
        }, 
        {
            "assetPath": "/Content/lang/bgm/bgm_m4a/bgm_03_019.m4a", 
            "bundle": {
                "/Content/lang/bgm/bgm_m4a/bgm_03_019.m4a": {
                    "hash": "MgEe/q5r/hij0/SaJ2Jn8g"
                }
            }
        }
    ], 
    "success": true, 
    "dungeons": [
        {
            "background_image_path": "/dff/static/lang/image/dungeon/203002_bg.png", 
            "order_no": 1, 
            "captures": [
                {
                    "sp_scores": [
                        {
                            "title": "Exploit the Griffon's weakness to wind attacks.", 
                            "battle_id": 303008
                        }
                    ], 
                    "image_path": "/dff/static/lang/image/enemy/403002.png", 
                    "tip_battle": {
                        "message": "The Griffon is vulnerable to <span class=\"red\">wind</span>, kupo, so use attacks that deal wind damage like <span class=\"red\">Aero Strike</span> to hit hard and fast!", 
                        "group_id": 420080, 
                        "id": 410080, 
                        "title": "Griffon"
                    }
                }
            ], 
            "is_new": true, 
            "rank": 0, 
            "closed_at": 2145938400, 
            "id": 203002, 
            "is_clear": false, 
            "button_style": "NORMAL", 
            "opened_at": 1424152800, 
            "world_id": 103001, 
            "type": 1, 
            "challenge_level": 36, 
            "is_unlocked": true, 
            "series_id": 103001, 
            "prizes": {
                "1": [
                    {
                        "id": 92000000, 
                        "type_name": "COMMON", 
                        "num": 3000, 
                        "image_path": "/dff/static/lang/image/common_item/92000000.png", 
                        "name": "Gil"
                    }
                ], 
                "3": [
                    {
                        "id": 40000008, 
                        "type_name": "ABILITY_MATERIAL", 
                        "num": 3, 
                        "image_path": "/dff/static/lang/image/ability_material/40000008/40000008_112.png", 
                        "name": "White Orb"
                    }, 
                    {
                        "id": 94000000, 
                        "type_name": "COMMON", 
                        "num": 1, 
                        "image_path": "/dff/static/lang/image/common_item/94000000.png", 
                        "name": "Stamina Shard"
                    }
                ], 
                "2": [
                    {
                        "id": 94000000, 
                        "type_name": "COMMON", 
                        "num": 1, 
                        "image_path": "/dff/static/lang/image/common_item/94000000.png", 
                        "name": "Stamina Shard"
                    }, 
                    {
                        "id": 91000000, 
                        "type_name": "COMMON", 
                        "num": 1, 
                        "image_path": "/dff/static/lang/image/common_item/91000000.png", 
                        "name": "Mythril"
                    }
                ]
            }, 
            "total_stamina": 37, 
            "epilogue": "The Djinn's curse extended beyond Kazus into the walls of Castle Sasune itself. King Sasune informed the Warriors of Light that Djinn made his fastness in the Sealed Cave, but defeating him would not be simple: the king's daughter, Princess Sara, held the mythril ring they needed to banish the Djinn, and she was nowhere to be found. Fearing she may have been kidnapped by the Djinn, the Warriors of Light hurried to the Sealed Cave to rescue her.", 
            "epilogue_image_path": "/dff/static/lang/image/dungeon/203002_epilogue.png", 
            "name": "Castle Sasune", 
            "bgm": "bgm_03_008", 
            "prologue": "The people of Kazus have been transformed into ghostly apparitions by the Djinn, a being of fire and darkness. Now the Warriors of Light travel to Castle Sasune in search of a mythril ring to banish the Djinn and seal him away.", 
            "is_master": false, 
            "prologue_image_path": "/dff/static/lang/image/dungeon/203002_prologue.png"
        }, 
        {
            "background_image_path": "/dff/static/lang/image/dungeon/203003_bg.png", 
            "order_no": 1, 
            "captures": [
                {
                    "sp_scores": [
                        {
                            "title": "Exploit Djinn's weakness to water attacks.", 
                            "battle_id": 303013
                        }, 
                        {
                            "title": "Exploit Djinn's weakness to ice attacks.", 
                            "battle_id": 303013
                        }
                    ], 
                    "image_path": "/dff/static/lang/image/enemy/403003.png", 
                    "tip_battle": {
                        "message": "The Djinn is vulnerable to <span class=\"red\">ice and water</span> attacks, kupo! Attack him with magic like <span class=\"red\">Blizzard and Water!</span>", 
                        "group_id": 420081, 
                        "id": 410081, 
                        "title": "Djinn"
                    }
                }
            ], 
            "is_new": false, 
            "rank": 0, 
            "closed_at": 2145938400, 
            "id": 203003, 
            "is_clear": false, 
            "button_style": "NORMAL", 
            "opened_at": 1424152800, 
            "world_id": 103001, 
            "type": 1, 
            "challenge_level": 36, 
            "is_unlocked": false, 
            "series_id": 103001, 
            "prizes": {
                "1": [
                    {
                        "id": 92000000, 
                        "type_name": "COMMON", 
                        "num": 3000, 
                        "image_path": "/dff/static/lang/image/common_item/92000000.png", 
                        "name": "Gil"
                    }
                ], 
                "3": [
                    {
                        "id": 40000048, 
                        "type_name": "ABILITY_MATERIAL", 
                        "num": 3, 
                        "image_path": "/dff/static/lang/image/ability_material/40000048/40000048_112.png", 
                        "name": "Earth Orb"
                    }, 
                    {
                        "id": 94000000, 
                        "type_name": "COMMON", 
                        "num": 1, 
                        "image_path": "/dff/static/lang/image/common_item/94000000.png", 
                        "name": "Stamina Shard"
                    }
                ], 
                "2": [
                    {
                        "id": 94000000, 
                        "type_name": "COMMON", 
                        "num": 1, 
                        "image_path": "/dff/static/lang/image/common_item/94000000.png", 
                        "name": "Stamina Shard"
                    }, 
                    {
                        "id": 91000000, 
                        "type_name": "COMMON", 
                        "num": 1, 
                        "image_path": "/dff/static/lang/image/common_item/91000000.png", 
                        "name": "Mythril"
                    }
                ]
            }, 
            "total_stamina": 46, 
            "epilogue": "At the height of the pitched battle with the Djinn, Sara held the mythril ring aloft and he vanished in a whirl of mist--the power of the ring had sealed him away in the cave once more. After their return to Castle Sasune, the Warriors of Light placed the ring in the waters of a sacred spring, and the Djinn's curse on the people was broken. In thanks, King Sasune gave the Warriors a magic canoe, and they set out once more.", 
            "epilogue_image_path": "/dff/static/lang/image/dungeon/203003_epilogue.png", 
            "name": "Sealed Cave", 
            "bgm": "bgm_03_009", 
            "prologue": "Princess Sara had not been kidnapped: she set out for the Sealed Cave on her own to banish the Djinn with the mythril ring. The Warriors of Light join her as she attempts to put an end to the Djinn's curse.", 
            "is_master": false, 
            "prologue_image_path": "/dff/static/lang/image/dungeon/203003_prologue.png"
        }, 
        {
            "background_image_path": "/dff/static/lang/image/dungeon/403005_bg.png", 
            "order_no": 1, 
            "captures": [
                {
                    "sp_scores": [
                        {
                            "title": "Defeat Medusa without being KO'd.", 
                            "battle_id": 503022
                        }
                    ], 
                    "image_path": "/dff/static/lang/image/enemy/403005.png", 
                    "tip_battle": {
                        "message": "Medusa's <span class=\"red\">Gaze</span> can turn a character to stone, kupo! Have <span class=\"red\">Stona and Esuna</span> at the ready to cure your party! Studying Medusa's myth may give some clues to defeating her...", 
                        "group_id": 410101, 
                        "id": 410101, 
                        "title": "Medusa"
                    }
                }
            ], 
            "is_new": false, 
            "rank": 0, 
            "closed_at": 2145938400, 
            "id": 403005, 
            "is_clear": false, 
            "button_style": "NORMAL", 
            "opened_at": 1434675600, 
            "world_id": 103001, 
            "type": 2, 
            "challenge_level": 72, 
            "is_unlocked": false, 
            "series_id": 103001, 
            "prizes": {
                "1": [
                    {
                        "id": 92000000, 
                        "type_name": "COMMON", 
                        "num": 14000, 
                        "image_path": "/dff/static/lang/image/common_item/92000000.png", 
                        "name": "Gil"
                    }
                ], 
                "3": [
                    {
                        "id": 40000039, 
                        "type_name": "ABILITY_MATERIAL", 
                        "num": 1, 
                        "image_path": "/dff/static/lang/image/ability_material/40000039/40000039_112.png", 
                        "name": "Greater Ice Orb"
                    }, 
                    {
                        "id": 40000014, 
                        "type_name": "ABILITY_MATERIAL", 
                        "num": 3, 
                        "image_path": "/dff/static/lang/image/ability_material/40000014/40000014_112.png", 
                        "name": "Greater Black Orb"
                    }
                ], 
                "2": [
                    {
                        "id": 94000000, 
                        "type_name": "COMMON", 
                        "num": 1, 
                        "image_path": "/dff/static/lang/image/common_item/94000000.png", 
                        "name": "Stamina Shard"
                    }, 
                    {
                        "id": 91000000, 
                        "type_name": "COMMON", 
                        "num": 1, 
                        "image_path": "/dff/static/lang/image/common_item/91000000.png", 
                        "name": "Mythril"
                    }
                ]
            }, 
            "total_stamina": 86, 
            "epilogue": "In the Tower of Owen, the Warriors of Light found Medusa trying to destroy the tower and send the Floating Continent crashing down. Though they were successful in stopping her, the tower was damaged and might have failed had Desch's memories not returned. Realizing he was one of the Ancients and the Guardian of the Tower, he risked his life to fix the tower furnace. Thanks to his bravery, the tower was saved and the maelstrom blocking passage to the north subsided, allowing the Warriors of Light to once again take to the seas.", 
            "epilogue_image_path": "/dff/static/lang/image/dungeon/403005_epilogue.png", 
            "name": "Tower of Owen", 
            "bgm": "bgm_03_019", 
            "prologue": "From the Gulgan's prophecy, the Warriors of Light have learned of the Tower of Owen, and now Desch is slowly regaining his memory, aiding their passage through the tower.", 
            "is_master": false, 
            "prologue_image_path": "/dff/static/lang/image/dungeon/403005_prologue.png"
        }, 
        {
            "background_image_path": "/dff/static/lang/image/dungeon/403003_bg.png", 
            "order_no": 1, 
            "captures": [
                {
                    "sp_scores": [
                        {
                            "title": "Exploit Djinn's weakness to water attacks.", 
                            "battle_id": 503013
                        }, 
                        {
                            "title": "Exploit Djinn's weakness to ice attacks.", 
                            "battle_id": 503013
                        }
                    ], 
                    "image_path": "/dff/static/lang/image/enemy/403003.png", 
                    "tip_battle": {
                        "message": "The Djinn is vulnerable to <span class=\"red\">ice and water</span> attacks, kupo! Attack him with magic like <span class=\"red\">Blizzard and Water!</span>", 
                        "group_id": 420081, 
                        "id": 410081, 
                        "title": "Djinn"
                    }
                }
            ], 
            "is_new": false, 
            "rank": 0, 
            "closed_at": 2145938400, 
            "id": 403003, 
            "is_clear": false, 
            "button_style": "NORMAL", 
            "opened_at": 1424152800, 
            "world_id": 103001, 
            "type": 2, 
            "challenge_level": 59, 
            "is_unlocked": false, 
            "series_id": 103001, 
            "prizes": {
                "1": [
                    {
                        "id": 92000000, 
                        "type_name": "COMMON", 
                        "num": 12000, 
                        "image_path": "/dff/static/lang/image/common_item/92000000.png", 
                        "name": "Gil"
                    }
                ], 
                "3": [
                    {
                        "id": 94000000, 
                        "type_name": "COMMON", 
                        "num": 1, 
                        "image_path": "/dff/static/lang/image/common_item/94000000.png", 
                        "name": "Stamina Shard"
                    }, 
                    {
                        "id": 40000004, 
                        "type_name": "ABILITY_MATERIAL", 
                        "num": 3, 
                        "image_path": "/dff/static/lang/image/ability_material/40000004/40000004_112.png", 
                        "name": "Greater Power Orb"
                    }
                ], 
                "2": [
                    {
                        "id": 94000000, 
                        "type_name": "COMMON", 
                        "num": 1, 
                        "image_path": "/dff/static/lang/image/common_item/94000000.png", 
                        "name": "Stamina Shard"
                    }, 
                    {
                        "id": 91000000, 
                        "type_name": "COMMON", 
                        "num": 1, 
                        "image_path": "/dff/static/lang/image/common_item/91000000.png", 
                        "name": "Mythril"
                    }
                ]
            }, 
            "total_stamina": 71, 
            "epilogue": "At the height of the pitched battle with the Djinn, Sara held the mythril ring aloft and he vanished in a whirl of mist--the power of the ring had sealed him away in the cave once more. After their return to Castle Sasune, the Warriors of Light placed the ring in the waters of a sacred spring, and the Djinn's curse on the people was broken. In thanks, King Sasune gave the Warriors a magic canoe, and they set out once more.", 
            "epilogue_image_path": "/dff/static/lang/image/dungeon/403003_epilogue.png", 
            "name": "Sealed Cave", 
            "bgm": "bgm_03_009", 
            "prologue": "Princess Sara had not been kidnapped: she set out for the Sealed Cave on her own to banish the Djinn with the mythril ring. The Warriors of Light join her as she attempts to put an end to the Djinn's curse.", 
            "is_master": false, 
            "prologue_image_path": "/dff/static/lang/image/dungeon/403003_prologue.png"
        }, 
        {
            "background_image_path": "/dff/static/lang/image/dungeon/203009_bg.png", 
            "order_no": 1, 
            "captures": [
                {
                    "sp_scores": [
                        {
                            "title": "Exploit the Kraken's weakness to lightning attacks.", 
                            "battle_id": 303038
                        }
                    ], 
                    "image_path": "/dff/static/lang/image/enemy/403009.png", 
                    "tip_battle": {
                        "message": "To stand up to the Kraken's powerful magic, you'll need abilities like <span class=\"red\">Magic Break, Shell, and Reflect</span>, kupo! The Kraken is vulnerable to <span class=\"red\">lightning</span>, though, so focus lightning attacks on this monster!", 
                        "group_id": 410105, 
                        "id": 410105, 
                        "title": "Kraken"
                    }
                }
            ], 
            "is_new": false, 
            "rank": 0, 
            "closed_at": 2145938400, 
            "id": 203009, 
            "is_clear": false, 
            "button_style": "NORMAL", 
            "opened_at": 1434675600, 
            "world_id": 103001, 
            "type": 1, 
            "challenge_level": 46, 
            "is_unlocked": false, 
            "series_id": 103001, 
            "prizes": {
                "1": [
                    {
                        "id": 92000000, 
                        "type_name": "COMMON", 
                        "num": 4000, 
                        "image_path": "/dff/static/lang/image/common_item/92000000.png", 
                        "name": "Gil"
                    }
                ], 
                "3": [
                    {
                        "id": 40000008, 
                        "type_name": "ABILITY_MATERIAL", 
                        "num": 3, 
                        "image_path": "/dff/static/lang/image/ability_material/40000008/40000008_112.png", 
                        "name": "White Orb"
                    }, 
                    {
                        "id": 24098003, 
                        "type_name": "EQUIPMENT", 
                        "num": 1, 
                        "image_path": "/dff/static/lang/image/equipment/24098003/24098003_03_112.png", 
                        "name": "Scarletite"
                    }
                ], 
                "2": [
                    {
                        "id": 94000000, 
                        "type_name": "COMMON", 
                        "num": 1, 
                        "image_path": "/dff/static/lang/image/common_item/94000000.png", 
                        "name": "Stamina Shard"
                    }, 
                    {
                        "id": 91000000, 
                        "type_name": "COMMON", 
                        "num": 1, 
                        "image_path": "/dff/static/lang/image/common_item/91000000.png", 
                        "name": "Mythril"
                    }
                ]
            }, 
            "total_stamina": 49, 
            "epilogue": "The Warriors of Light arrived at the Cave of Tides to find the Kraken lying in wait for them. Like Medusa in the Tower of Owen, the Kraken was a servant of Master Xande. Though the party was successful in defeating the Kraken, the Priestess Aria died saving their lives from the creature's attack.", 
            "epilogue_image_path": "/dff/static/lang/image/dungeon/203009_epilogue.png", 
            "name": "Cave of Tides", 
            "bgm": "bgm_03_009", 
            "prologue": "The power of the Water Crystal has been lost, covering the Surface World in a dark flood. The party makes for the Cave of Tides to restore the crystal's light.", 
            "is_master": false, 
            "prologue_image_path": "/dff/static/lang/image/dungeon/203009_prologue.png"
        }, 
        {
            "background_image_path": "/dff/static/lang/image/dungeon/403007_bg.png", 
            "order_no": 1, 
            "captures": [
                {
                    "sp_scores": [
                        {
                            "title": "Exploit the Salamander's weakness to water attacks.", 
                            "battle_id": 503029
                        }, 
                        {
                            "title": "Exploit the Salamander's weakness to ice attacks.", 
                            "battle_id": 503029
                        }
                    ], 
                    "image_path": "/dff/static/lang/image/enemy/403007.png", 
                    "tip_battle": {
                        "message": "Salamander uses a flame attack that <span class=\"red\">hits the whole party!</span> Use its weakness to <span class=\"red\">water and ice</span> to win before your party is barbecue, kupo!", 
                        "group_id": 410103, 
                        "id": 410103, 
                        "title": "Salamander"
                    }
                }
            ], 
            "is_new": false, 
            "rank": 0, 
            "closed_at": 2145938400, 
            "id": 403007, 
            "is_clear": false, 
            "button_style": "NORMAL", 
            "opened_at": 1434675600, 
            "world_id": 103001, 
            "type": 2, 
            "challenge_level": 77, 
            "is_unlocked": false, 
            "series_id": 103001, 
            "prizes": {
                "1": [
                    {
                        "id": 92000000, 
                        "type_name": "COMMON", 
                        "num": 14000, 
                        "image_path": "/dff/static/lang/image/common_item/92000000.png", 
                        "name": "Gil"
                    }
                ], 
                "3": [
                    {
                        "id": 24099004, 
                        "type_name": "EQUIPMENT", 
                        "num": 1, 
                        "image_path": "/dff/static/lang/image/equipment/24099004/24099004_04_112.png", 
                        "name": "Large Adamantite"
                    }, 
                    {
                        "id": 40000059, 
                        "type_name": "ABILITY_MATERIAL", 
                        "num": 1, 
                        "image_path": "/dff/static/lang/image/ability_material/40000059/40000059_112.png", 
                        "name": "Greater Holy Orb"
                    }
                ], 
                "2": [
                    {
                        "id": 94000000, 
                        "type_name": "COMMON", 
                        "num": 1, 
                        "image_path": "/dff/static/lang/image/common_item/94000000.png", 
                        "name": "Stamina Shard"
                    }, 
                    {
                        "id": 91000000, 
                        "type_name": "COMMON", 
                        "num": 1, 
                        "image_path": "/dff/static/lang/image/common_item/91000000.png", 
                        "name": "Mythril"
                    }
                ]
            }, 
            "total_stamina": 69, 
            "epilogue": "The Warriors of Light made their way into the Molten Cave and defeated Gutsco, who had used the Fire Crystal to transform into the powerful Salamander. Granted new strength from the crystal, the party returned to the Dwarven Hollows where they received word that the village of Tokkul was in flames.", 
            "epilogue_image_path": "/dff/static/lang/image/dungeon/403007_epilogue.png", 
            "name": "Molten Cave", 
            "bgm": "bgm_03_009", 
            "prologue": "The Warriors of Light make for the Molten Cave to settle the score with Gutsco, the thief who stole the dwarves' Horns of Ice.", 
            "is_master": false, 
            "prologue_image_path": "/dff/static/lang/image/dungeon/403007_prologue.png"
        }, 
        {
            "background_image_path": "/dff/static/lang/image/dungeon/403009_bg.png", 
            "order_no": 1, 
            "captures": [
                {
                    "sp_scores": [
                        {
                            "title": "Exploit the Kraken's weakness to lightning attacks.", 
                            "battle_id": 503038
                        }
                    ], 
                    "image_path": "/dff/static/lang/image/enemy/403009.png", 
                    "tip_battle": {
                        "message": "To stand up to the Kraken's powerful magic, you'll need abilities like <span class=\"red\">Magic Break, Shell, and Reflect</span>, kupo! The Kraken is vulnerable to <span class=\"red\">lightning</span>, though, so focus lightning attacks on this monster!", 
                        "group_id": 410105, 
                        "id": 410105, 
                        "title": "Kraken"
                    }
                }
            ], 
            "is_new": false, 
            "rank": 0, 
            "closed_at": 2145938400, 
            "id": 403009, 
            "is_clear": false, 
            "button_style": "NORMAL", 
            "opened_at": 1434675600, 
            "world_id": 103001, 
            "type": 2, 
            "challenge_level": 81, 
            "is_unlocked": false, 
            "series_id": 103001, 
            "prizes": {
                "1": [
                    {
                        "id": 92000000, 
                        "type_name": "COMMON", 
                        "num": 14000, 
                        "image_path": "/dff/static/lang/image/common_item/92000000.png", 
                        "name": "Gil"
                    }
                ], 
                "3": [
                    {
                        "id": 94000000, 
                        "type_name": "COMMON", 
                        "num": 1, 
                        "image_path": "/dff/static/lang/image/common_item/94000000.png", 
                        "name": "Stamina Shard"
                    }, 
                    {
                        "id": 40000015, 
                        "type_name": "ABILITY_MATERIAL", 
                        "num": 1, 
                        "image_path": "/dff/static/lang/image/ability_material/40000015/40000015_112.png", 
                        "name": "Major Black Orb"
                    }
                ], 
                "2": [
                    {
                        "id": 40000039, 
                        "type_name": "ABILITY_MATERIAL", 
                        "num": 1, 
                        "image_path": "/dff/static/lang/image/ability_material/40000039/40000039_112.png", 
                        "name": "Greater Ice Orb"
                    }, 
                    {
                        "id": 91000000, 
                        "type_name": "COMMON", 
                        "num": 1, 
                        "image_path": "/dff/static/lang/image/common_item/91000000.png", 
                        "name": "Mythril"
                    }
                ]
            }, 
            "total_stamina": 69, 
            "epilogue": "The Warriors of Light arrived at the Cave of Tides to find the Kraken lying in wait for them. Like Medusa in the Tower of Owen, the Kraken was a servant of Master Xande. Though the party was successful in defeating the Kraken, the Priestess Aria died saving their lives from the creature's attack.", 
            "epilogue_image_path": "/dff/static/lang/image/dungeon/403009_epilogue.png", 
            "name": "Cave of Tides", 
            "bgm": "bgm_03_009", 
            "prologue": "The power of the Water Crystal has been lost, covering the Surface World in a dark flood. The party makes for the Cave of Tides to restore the crystal's light.", 
            "is_master": false, 
            "prologue_image_path": "/dff/static/lang/image/dungeon/403009_prologue.png"
        }, 
        {
            "background_image_path": "/dff/static/lang/image/dungeon/203010_bg.png", 
            "order_no": 1, 
            "captures": [
                {
                    "sp_scores": [
                        {
                            "title": "Defeat Goldor without being KO'd.", 
                            "battle_id": 303041
                        }, 
                        {
                            "title": "Silence Goldor.", 
                            "battle_id": 303041
                        }
                    ], 
                    "image_path": "/dff/static/lang/image/enemy/403010.png", 
                    "tip_battle": {
                        "message": "Goldor has a fondness for <span class=\"red\">debuff magic</span>, kupo! Bring along abilities that can <span class=\"red\">Silence</span>, and you'll have a much easier time!", 
                        "group_id": 410106, 
                        "id": 410106, 
                        "title": "Goldor"
                    }
                }
            ], 
            "is_new": false, 
            "rank": 0, 
            "closed_at": 2145938400, 
            "id": 203010, 
            "is_clear": false, 
            "button_style": "NORMAL", 
            "opened_at": 1434675600, 
            "world_id": 103001, 
            "type": 1, 
            "challenge_level": 47, 
            "is_unlocked": false, 
            "series_id": 103001, 
            "prizes": {
                "1": [
                    {
                        "id": 92000000, 
                        "type_name": "COMMON", 
                        "num": 4000, 
                        "image_path": "/dff/static/lang/image/common_item/92000000.png", 
                        "name": "Gil"
                    }
                ], 
                "3": [
                    {
                        "id": 40000053, 
                        "type_name": "ABILITY_MATERIAL", 
                        "num": 3, 
                        "image_path": "/dff/static/lang/image/ability_material/40000053/40000053_112.png", 
                        "name": "Wind Orb"
                    }, 
                    {
                        "id": 94000000, 
                        "type_name": "COMMON", 
                        "num": 1, 
                        "image_path": "/dff/static/lang/image/common_item/94000000.png", 
                        "name": "Stamina Shard"
                    }
                ], 
                "2": [
                    {
                        "id": 70000003, 
                        "type_name": "GROW_EGG", 
                        "num": 1, 
                        "image_path": "/dff/static/lang/image/growegg/70000003/70000003_112.png", 
                        "name": "Growth Egg"
                    }, 
                    {
                        "id": 91000000, 
                        "type_name": "COMMON", 
                        "num": 1, 
                        "image_path": "/dff/static/lang/image/common_item/91000000.png", 
                        "name": "Mythril"
                    }
                ]
            }, 
            "total_stamina": 37, 
            "epilogue": "The Warriors of Light learned that Goldor, the man who chained the Enterprise, possessed a crystal. Making their way to his manor, they defeated him, but the crystal was destroyed in the fight. They retrieved the key to the chains and returned to Amur filled with regret over the crystal's loss.", 
            "epilogue_image_path": "/dff/static/lang/image/dungeon/203010_epilogue.png", 
            "name": "Goldor Manor", 
            "bgm": "bgm_03_002", 
            "prologue": "As the waters recede following the death of the Kraken, the party is caught in the collapsing Cave of Tides. They wake in the Inn at Amur, miraculously alive, yet find their airship Enterprise in chains.", 
            "is_master": false, 
            "prologue_image_path": "/dff/static/lang/image/dungeon/203010_prologue.png"
        }, 
        {
            "background_image_path": "/dff/static/lang/image/dungeon/203007_bg.png", 
            "order_no": 1, 
            "captures": [
                {
                    "sp_scores": [
                        {
                            "title": "Exploit the Salamander's weakness to water attacks.", 
                            "battle_id": 303029
                        }, 
                        {
                            "title": "Exploit the Salamander's weakness to ice attacks.", 
                            "battle_id": 303029
                        }
                    ], 
                    "image_path": "/dff/static/lang/image/enemy/403007.png", 
                    "tip_battle": {
                        "message": "Salamander uses a flame attack that <span class=\"red\">hits the whole party!</span> Use its weakness to <span class=\"red\">water and ice</span> to win before your party is barbecue, kupo!", 
                        "group_id": 410103, 
                        "id": 410103, 
                        "title": "Salamander"
                    }
                }
            ], 
            "is_new": false, 
            "rank": 0, 
            "closed_at": 2145938400, 
            "id": 203007, 
            "is_clear": false, 
            "button_style": "NORMAL", 
            "opened_at": 1434675600, 
            "world_id": 103001, 
            "type": 1, 
            "challenge_level": 46, 
            "is_unlocked": false, 
            "series_id": 103001, 
            "prizes": {
                "1": [
                    {
                        "id": 92000000, 
                        "type_name": "COMMON", 
                        "num": 4000, 
                        "image_path": "/dff/static/lang/image/common_item/92000000.png", 
                        "name": "Gil"
                    }
                ], 
                "3": [
                    {
                        "id": 40000058, 
                        "type_name": "ABILITY_MATERIAL", 
                        "num": 3, 
                        "image_path": "/dff/static/lang/image/ability_material/40000058/40000058_112.png", 
                        "name": "Holy Orb"
                    }, 
                    {
                        "id": 70000003, 
                        "type_name": "GROW_EGG", 
                        "num": 1, 
                        "image_path": "/dff/static/lang/image/growegg/70000003/70000003_112.png", 
                        "name": "Growth Egg"
                    }
                ], 
                "2": [
                    {
                        "id": 70000003, 
                        "type_name": "GROW_EGG", 
                        "num": 1, 
                        "image_path": "/dff/static/lang/image/growegg/70000003/70000003_112.png", 
                        "name": "Growth Egg"
                    }, 
                    {
                        "id": 10300300, 
                        "type_name": "BUDDY", 
                        "num": 1, 
                        "image_path": "/dff/static/lang/image/buddy/10300300/10300300.png", 
                        "name": "Refia"
                    }
                ]
            }, 
            "total_stamina": 49, 
            "epilogue": "The Warriors of Light made their way into the Molten Cave and defeated Gutsco, who had used the Fire Crystal to transform into the powerful Salamander. Granted new strength from the crystal, the party returned to the Dwarven Hollows where they received word that the village of Tokkul was in flames.", 
            "epilogue_image_path": "/dff/static/lang/image/dungeon/203007_epilogue.png", 
            "name": "Molten Cave", 
            "bgm": "bgm_03_009", 
            "prologue": "The Warriors of Light make for the Molten Cave to settle the score with Gutsco, the thief who stole the dwarves' Horns of Ice.", 
            "is_master": false, 
            "prologue_image_path": "/dff/static/lang/image/dungeon/203007_prologue.png"
        }, 
        {
            "background_image_path": "/dff/static/lang/image/dungeon/403010_bg.png", 
            "order_no": 1, 
            "captures": [
                {
                    "sp_scores": [
                        {
                            "title": "Defeat Goldor without being KO'd.", 
                            "battle_id": 503041
                        }, 
                        {
                            "title": "Silence Goldor.", 
                            "battle_id": 503041
                        }
                    ], 
                    "image_path": "/dff/static/lang/image/enemy/403010.png", 
                    "tip_battle": {
                        "message": "Goldor has a fondness for <span class=\"red\">debuff magic</span>, kupo! Bring along abilities that can <span class=\"red\">Silence</span>, and you'll have a much easier time!", 
                        "group_id": 410106, 
                        "id": 410106, 
                        "title": "Goldor"
                    }
                }
            ], 
            "is_new": false, 
            "rank": 0, 
            "closed_at": 2145938400, 
            "id": 403010, 
            "is_clear": false, 
            "button_style": "NORMAL", 
            "opened_at": 1434675600, 
            "world_id": 103001, 
            "type": 2, 
            "challenge_level": 84, 
            "is_unlocked": false, 
            "series_id": 103001, 
            "prizes": {
                "1": [
                    {
                        "id": 92000000, 
                        "type_name": "COMMON", 
                        "num": 14000, 
                        "image_path": "/dff/static/lang/image/common_item/92000000.png", 
                        "name": "Gil"
                    }
                ], 
                "3": [
                    {
                        "id": 40000009, 
                        "type_name": "ABILITY_MATERIAL", 
                        "num": 3, 
                        "image_path": "/dff/static/lang/image/ability_material/40000009/40000009_112.png", 
                        "name": "Greater White Orb"
                    }, 
                    {
                        "id": 40000049, 
                        "type_name": "ABILITY_MATERIAL", 
                        "num": 1, 
                        "image_path": "/dff/static/lang/image/ability_material/40000049/40000049_112.png", 
                        "name": "Greater Earth Orb"
                    }
                ], 
                "2": [
                    {
                        "id": 94000000, 
                        "type_name": "COMMON", 
                        "num": 1, 
                        "image_path": "/dff/static/lang/image/common_item/94000000.png", 
                        "name": "Stamina Shard"
                    }, 
                    {
                        "id": 91000000, 
                        "type_name": "COMMON", 
                        "num": 1, 
                        "image_path": "/dff/static/lang/image/common_item/91000000.png", 
                        "name": "Mythril"
                    }
                ]
            }, 
            "total_stamina": 52, 
            "epilogue": "The Warriors of Light learned that Goldor, the man who chained the Enterprise, possessed a crystal. Making their way to his manor, they defeated him, but the crystal was destroyed in the fight. They retrieved the key to the chains and returned to Amur filled with regret over the crystal's loss.", 
            "epilogue_image_path": "/dff/static/lang/image/dungeon/403010_epilogue.png", 
            "name": "Goldor Manor", 
            "bgm": "bgm_03_002", 
            "prologue": "As the waters recede following the death of the Kraken, the party is caught in the collapsing Cave of Tides. They wake in the Inn at Amur, miraculously alive, yet find their airship Enterprise in chains.", 
            "is_master": false, 
            "prologue_image_path": "/dff/static/lang/image/dungeon/403010_prologue.png"
        }, 
        {
            "background_image_path": "/dff/static/lang/image/dungeon/203006_bg.png", 
            "order_no": 1, 
            "captures": [
                {
                    "sp_scores": [
                        {
                            "title": "Defeat Gutsco without being KO'd.", 
                            "battle_id": 303025
                        }
                    ], 
                    "image_path": "/dff/static/lang/image/enemy/403006.png", 
                    "tip_battle": {
                        "message": "Gutsco gets <span class=\"red\">2 actions per turn</span>, kupo! <span class=\"red\">Slow or Paralyze</span> him to keep him from running away with the victory!", 
                        "group_id": 410102, 
                        "id": 410102, 
                        "title": "Gutsco"
                    }
                }
            ], 
            "is_new": false, 
            "rank": 0, 
            "closed_at": 2145938400, 
            "id": 203006, 
            "is_clear": false, 
            "button_style": "NORMAL", 
            "opened_at": 1434675600, 
            "world_id": 103001, 
            "type": 1, 
            "challenge_level": 45, 
            "is_unlocked": false, 
            "series_id": 103001, 
            "prizes": {
                "1": [
                    {
                        "id": 92000000, 
                        "type_name": "COMMON", 
                        "num": 4000, 
                        "image_path": "/dff/static/lang/image/common_item/92000000.png", 
                        "name": "Gil"
                    }
                ], 
                "3": [
                    {
                        "id": 40000033, 
                        "type_name": "ABILITY_MATERIAL", 
                        "num": 3, 
                        "image_path": "/dff/static/lang/image/ability_material/40000033/40000033_112.png", 
                        "name": "Fire Orb"
                    }, 
                    {
                        "id": 94000000, 
                        "type_name": "COMMON", 
                        "num": 1, 
                        "image_path": "/dff/static/lang/image/common_item/94000000.png", 
                        "name": "Stamina Shard"
                    }
                ], 
                "2": [
                    {
                        "id": 70000003, 
                        "type_name": "GROW_EGG", 
                        "num": 1, 
                        "image_path": "/dff/static/lang/image/growegg/70000003/70000003_112.png", 
                        "name": "Growth Egg"
                    }, 
                    {
                        "id": 91000000, 
                        "type_name": "COMMON", 
                        "num": 1, 
                        "image_path": "/dff/static/lang/image/common_item/91000000.png", 
                        "name": "Mythril"
                    }
                ]
            }, 
            "total_stamina": 37, 
            "epilogue": "The Warriors of Light defeated the thief Gutsco and retrieved the dwarves' Horn of Ice, but a mysterious shadow trailed them as they returned the horn to the altar in the Dwarven Hollows. No sooner was the horn replaced than Gutsco emerged from the shadow and stole both of the horns, which he took to the Molten Cave in order to open the path to his true goal: the Fire Crystal.", 
            "epilogue_image_path": "/dff/static/lang/image/dungeon/203006_epilogue.png", 
            "name": "Subterranean Lake", 
            "bgm": "bgm_03_009", 
            "prologue": "The party arrives in the Dwarven Hollows to find the dwarves in a furor over the theft of one of their precious Horns of Ice. At the dwarves' request, the party heads for the subterranean lake to retrieve the horn.", 
            "is_master": false, 
            "prologue_image_path": "/dff/static/lang/image/dungeon/203006_prologue.png"
        }, 
        {
            "background_image_path": "/dff/static/lang/image/dungeon/403002_bg.png", 
            "order_no": 1, 
            "captures": [
                {
                    "sp_scores": [
                        {
                            "title": "Exploit the Griffon's weakness to wind attacks.", 
                            "battle_id": 503008
                        }
                    ], 
                    "image_path": "/dff/static/lang/image/enemy/403002.png", 
                    "tip_battle": {
                        "message": "The Griffon is vulnerable to <span class=\"red\">wind</span>, kupo, so use attacks that deal wind damage like <span class=\"red\">Aero Strike</span> to hit hard and fast!", 
                        "group_id": 420080, 
                        "id": 410080, 
                        "title": "Griffon"
                    }
                }
            ], 
            "is_new": false, 
            "rank": 0, 
            "closed_at": 2145938400, 
            "id": 403002, 
            "is_clear": false, 
            "button_style": "NORMAL", 
            "opened_at": 1424152800, 
            "world_id": 103001, 
            "type": 2, 
            "challenge_level": 57, 
            "is_unlocked": false, 
            "series_id": 103001, 
            "prizes": {
                "1": [
                    {
                        "id": 92000000, 
                        "type_name": "COMMON", 
                        "num": 12000, 
                        "image_path": "/dff/static/lang/image/common_item/92000000.png", 
                        "name": "Gil"
                    }
                ], 
                "3": [
                    {
                        "id": 40000014, 
                        "type_name": "ABILITY_MATERIAL", 
                        "num": 3, 
                        "image_path": "/dff/static/lang/image/ability_material/40000014/40000014_112.png", 
                        "name": "Greater Black Orb"
                    }, 
                    {
                        "id": 94000000, 
                        "type_name": "COMMON", 
                        "num": 1, 
                        "image_path": "/dff/static/lang/image/common_item/94000000.png", 
                        "name": "Stamina Shard"
                    }
                ], 
                "2": [
                    {
                        "id": 94000000, 
                        "type_name": "COMMON", 
                        "num": 1, 
                        "image_path": "/dff/static/lang/image/common_item/94000000.png", 
                        "name": "Stamina Shard"
                    }, 
                    {
                        "id": 91000000, 
                        "type_name": "COMMON", 
                        "num": 1, 
                        "image_path": "/dff/static/lang/image/common_item/91000000.png", 
                        "name": "Mythril"
                    }
                ]
            }, 
            "total_stamina": 57, 
            "epilogue": "The Djinn's curse extended beyond Kazus into the walls of Castle Sasune itself. King Sasune informed the Warriors of Light that Djinn made his fastness in the Sealed Cave, but defeating him would not be simple: the king's daughter, Princess Sara, held the mythril ring they needed to banish the Djinn, and she was nowhere to be found. Fearing she may have been kidnapped by the Djinn, the Warriors of Light hurried to the Sealed Cave to rescue her.", 
            "epilogue_image_path": "/dff/static/lang/image/dungeon/403002_epilogue.png", 
            "name": "Castle Sasune", 
            "bgm": "bgm_03_008", 
            "prologue": "The people of Kazus have been transformed into ghostly apparitions by the Djinn, a being of fire and darkness. Now the Warriors of Light travel to Castle Sasune in search of a mythril ring to banish the Djinn and seal him away.", 
            "is_master": false, 
            "prologue_image_path": "/dff/static/lang/image/dungeon/403002_prologue.png"
        }, 
        {
            "background_image_path": "/dff/static/lang/image/dungeon/203008_bg.png", 
            "order_no": 1, 
            "captures": [
                {
                    "sp_scores": [
                        {
                            "title": "Exploit Hein's window of weakness to fire attacks.", 
                            "battle_id": 303034
                        }, 
                        {
                            "title": "Exploit Hein's window of weakness to ice attacks.", 
                            "battle_id": 303034
                        }, 
                        {
                            "title": "Exploit Hein's window of weakness to lightning attacks.", 
                            "battle_id": 303034
                        }
                    ], 
                    "image_path": "/dff/static/lang/image/enemy/403008.png", 
                    "tip_battle": {
                        "message": "Hein has extremely high evasion, so it's really <span class=\"red\">hard to land a physical attack</span> on him, kupo! Not only that, every 3 turns he uses <span class=\"red\">Barrier Shift</span> to change his elemental weakness. You'll need a whole suite of <span class=\"red\">fire, lightning, and ice magic</span> to bring him down!", 
                        "group_id": 410104, 
                        "id": 410104, 
                        "title": "Hein"
                    }
                }
            ], 
            "is_new": false, 
            "rank": 0, 
            "closed_at": 2145938400, 
            "id": 203008, 
            "is_clear": false, 
            "button_style": "NORMAL", 
            "opened_at": 1434675600, 
            "world_id": 103001, 
            "type": 1, 
            "challenge_level": 48, 
            "is_unlocked": false, 
            "series_id": 103001, 
            "prizes": {
                "1": [
                    {
                        "id": 92000000, 
                        "type_name": "COMMON", 
                        "num": 4000, 
                        "image_path": "/dff/static/lang/image/common_item/92000000.png", 
                        "name": "Gil"
                    }
                ], 
                "3": [
                    {
                        "id": 40000038, 
                        "type_name": "ABILITY_MATERIAL", 
                        "num": 3, 
                        "image_path": "/dff/static/lang/image/ability_material/40000038/40000038_112.png", 
                        "name": "Ice Orb"
                    }, 
                    {
                        "id": 94000000, 
                        "type_name": "COMMON", 
                        "num": 1, 
                        "image_path": "/dff/static/lang/image/common_item/94000000.png", 
                        "name": "Stamina Shard"
                    }
                ], 
                "2": [
                    {
                        "id": 70000003, 
                        "type_name": "GROW_EGG", 
                        "num": 1, 
                        "image_path": "/dff/static/lang/image/growegg/70000003/70000003_112.png", 
                        "name": "Growth Egg"
                    }, 
                    {
                        "id": 101000140, 
                        "type_name": "MEMORY_CRYSTAL", 
                        "num": 1, 
                        "image_path": "/dff/static/lang/image/memory_crystal/101000140/101000140_112.png", 
                        "name": "White Mage Memory Crystal"
                    }
                ]
            }, 
            "total_stamina": 37, 
            "epilogue": "The evil wizard Hein had been using King Argus's soldiers to further his plans for world domination. The party made their way to the throne at the top of Castle Hein where they found the wizard himself, a skeletal creature descended into darkness. Though Hein's Barrier Shift made victory no certain thing, the Warriors of Light prevailed, lifting the curse on the Elder Tree of the Living Woods.", 
            "epilogue_image_path": "/dff/static/lang/image/dungeon/203008_epilogue.png", 
            "name": "Hein's Castle", 
            "bgm": "bgm_03_021", 
            "prologue": "The Warriors of Light are taken captive in Tokkul and thrown in the dungeons of Castle Hein. Now they must free themselves and put an end to Hein's evil schemes.", 
            "is_master": false, 
            "prologue_image_path": "/dff/static/lang/image/dungeon/203008_prologue.png"
        }, 
        {
            "background_image_path": "/dff/static/lang/image/dungeon/403004_bg.png", 
            "order_no": 1, 
            "captures": [
                {
                    "sp_scores": [
                        {
                            "title": "Afflict the Giant Rat with Silence.", 
                            "battle_id": 503017
                        }
                    ], 
                    "image_path": "/dff/static/lang/image/enemy/403004.png", 
                    "tip_battle": {
                        "message": "The Giant Rat is a vile beast with no vulnerabilities, kupo! It uses all sorts of elemental magic, so try to land a <span class=\"red\">Silence</span> on it!", 
                        "group_id": 420082, 
                        "id": 410082, 
                        "title": "Giant Rat"
                    }
                }
            ], 
            "is_new": false, 
            "rank": 0, 
            "closed_at": 2145938400, 
            "id": 403004, 
            "is_clear": false, 
            "button_style": "NORMAL", 
            "opened_at": 1424152800, 
            "world_id": 103001, 
            "type": 2, 
            "challenge_level": 62, 
            "is_unlocked": false, 
            "series_id": 103001, 
            "prizes": {
                "1": [
                    {
                        "id": 92000000, 
                        "type_name": "COMMON", 
                        "num": 12000, 
                        "image_path": "/dff/static/lang/image/common_item/92000000.png", 
                        "name": "Gil"
                    }
                ], 
                "3": [
                    {
                        "id": 24099004, 
                        "type_name": "EQUIPMENT", 
                        "num": 1, 
                        "image_path": "/dff/static/lang/image/equipment/24099004/24099004_04_112.png", 
                        "name": "Large Adamantite"
                    }, 
                    {
                        "id": 94000000, 
                        "type_name": "COMMON", 
                        "num": 1, 
                        "image_path": "/dff/static/lang/image/common_item/94000000.png", 
                        "name": "Stamina Shard"
                    }
                ], 
                "2": [
                    {
                        "id": 94000000, 
                        "type_name": "COMMON", 
                        "num": 1, 
                        "image_path": "/dff/static/lang/image/common_item/94000000.png", 
                        "name": "Stamina Shard"
                    }, 
                    {
                        "id": 91000000, 
                        "type_name": "COMMON", 
                        "num": 1, 
                        "image_path": "/dff/static/lang/image/common_item/91000000.png", 
                        "name": "Mythril"
                    }
                ]
            }, 
            "total_stamina": 61, 
            "epilogue": "After searching the Nepto Temple, the Warriors of Light discovered that the statue of the Nepto Dragon was missing one of its eyes, a glimmering jewel. The Warriors shrank themselves to enter a passage in the statue's mouth, and soon found the Giant Rat responsible for the jewel's theft. They defeated the rat and replaced the jewel in the statue, thereby calming the Nepto Dragon who entrusted them with the Fang of Water before returning to its slumber.", 
            "epilogue_image_path": "/dff/static/lang/image/dungeon/403004_epilogue.png", 
            "name": "Nepto Temple", 
            "bgm": "bgm_03_013", 
            "prologue": "The once peaceful town of Vikings' Cove has faced numerous attacks by the Nepto Dragon, which has grown violent of late. A pall lies over the village, and the Warriors of Light venture to the Nepto Temple to seek out answers.", 
            "is_master": false, 
            "prologue_image_path": "/dff/static/lang/image/dungeon/403004_prologue.png"
        }, 
        {
            "background_image_path": "/dff/static/lang/image/dungeon/403006_bg.png", 
            "order_no": 1, 
            "captures": [
                {
                    "sp_scores": [
                        {
                            "title": "Defeat Gutsco without being KO'd.", 
                            "battle_id": 503025
                        }
                    ], 
                    "image_path": "/dff/static/lang/image/enemy/403006.png", 
                    "tip_battle": {
                        "message": "Gutsco gets <span class=\"red\">2 actions per turn</span>, kupo! <span class=\"red\">Slow or Paralyze</span> him to keep him from running away with the victory!", 
                        "group_id": 410102, 
                        "id": 410102, 
                        "title": "Gutsco"
                    }
                }
            ], 
            "is_new": false, 
            "rank": 0, 
            "closed_at": 2145938400, 
            "id": 403006, 
            "is_clear": false, 
            "button_style": "NORMAL", 
            "opened_at": 1434675600, 
            "world_id": 103001, 
            "type": 2, 
            "challenge_level": 74, 
            "is_unlocked": false, 
            "series_id": 103001, 
            "prizes": {
                "1": [
                    {
                        "id": 92000000, 
                        "type_name": "COMMON", 
                        "num": 14000, 
                        "image_path": "/dff/static/lang/image/common_item/92000000.png", 
                        "name": "Gil"
                    }
                ], 
                "3": [
                    {
                        "id": 94000000, 
                        "type_name": "COMMON", 
                        "num": 1, 
                        "image_path": "/dff/static/lang/image/common_item/94000000.png", 
                        "name": "Stamina Shard"
                    }, 
                    {
                        "id": 40000004, 
                        "type_name": "ABILITY_MATERIAL", 
                        "num": 3, 
                        "image_path": "/dff/static/lang/image/ability_material/40000004/40000004_112.png", 
                        "name": "Greater Power Orb"
                    }
                ], 
                "2": [
                    {
                        "id": 40000049, 
                        "type_name": "ABILITY_MATERIAL", 
                        "num": 1, 
                        "image_path": "/dff/static/lang/image/ability_material/40000049/40000049_112.png", 
                        "name": "Greater Earth Orb"
                    }, 
                    {
                        "id": 91000000, 
                        "type_name": "COMMON", 
                        "num": 1, 
                        "image_path": "/dff/static/lang/image/common_item/91000000.png", 
                        "name": "Mythril"
                    }
                ]
            }, 
            "total_stamina": 52, 
            "epilogue": "The Warriors of Light defeated the thief Gutsco and retrieved the dwarves' Horn of Ice, but a mysterious shadow trailed them as they returned the horn to the altar in the Dwarven Hollows. No sooner was the horn replaced than Gutsco emerged from the shadow and stole both of the horns, which he took to the Molten Cave in order to open the path to his true goal: the Fire Crystal.", 
            "epilogue_image_path": "/dff/static/lang/image/dungeon/403006_epilogue.png", 
            "name": "Subterranean Lake", 
            "bgm": "bgm_03_009", 
            "prologue": "The party arrives in the Dwarven Hollows to find the dwarves in a furor over the theft of one of their precious Horns of Ice. At the dwarves' request, the party heads for the subterranean lake to retrieve the horn.", 
            "is_master": false, 
            "prologue_image_path": "/dff/static/lang/image/dungeon/403006_prologue.png"
        }, 
        {
            "background_image_path": "/dff/static/lang/image/dungeon/203004_bg.png", 
            "order_no": 1, 
            "captures": [
                {
                    "sp_scores": [
                        {
                            "title": "Afflict the Giant Rat with Silence.", 
                            "battle_id": 303017
                        }
                    ], 
                    "image_path": "/dff/static/lang/image/enemy/403004.png", 
                    "tip_battle": {
                        "message": "The Giant Rat is a vile beast with no vulnerabilities, kupo! It uses all sorts of elemental magic, so try to land a <span class=\"red\">Silence</span> on it!", 
                        "group_id": 420082, 
                        "id": 410082, 
                        "title": "Giant Rat"
                    }
                }
            ], 
            "is_new": false, 
            "rank": 0, 
            "closed_at": 2145938400, 
            "id": 203004, 
            "is_clear": false, 
            "button_style": "NORMAL", 
            "opened_at": 1424152800, 
            "world_id": 103001, 
            "type": 1, 
            "challenge_level": 37, 
            "is_unlocked": false, 
            "series_id": 103001, 
            "prizes": {
                "1": [
                    {
                        "id": 92000000, 
                        "type_name": "COMMON", 
                        "num": 3000, 
                        "image_path": "/dff/static/lang/image/common_item/92000000.png", 
                        "name": "Gil"
                    }
                ], 
                "3": [
                    {
                        "id": 40000053, 
                        "type_name": "ABILITY_MATERIAL", 
                        "num": 3, 
                        "image_path": "/dff/static/lang/image/ability_material/40000053/40000053_112.png", 
                        "name": "Wind Orb"
                    }, 
                    {
                        "id": 94000000, 
                        "type_name": "COMMON", 
                        "num": 1, 
                        "image_path": "/dff/static/lang/image/common_item/94000000.png", 
                        "name": "Stamina Shard"
                    }
                ], 
                "2": [
                    {
                        "id": 94000000, 
                        "type_name": "COMMON", 
                        "num": 1, 
                        "image_path": "/dff/static/lang/image/common_item/94000000.png", 
                        "name": "Stamina Shard"
                    }, 
                    {
                        "id": 91000000, 
                        "type_name": "COMMON", 
                        "num": 1, 
                        "image_path": "/dff/static/lang/image/common_item/91000000.png", 
                        "name": "Mythril"
                    }
                ]
            }, 
            "total_stamina": 41, 
            "epilogue": "After searching the Nepto Temple, the Warriors of Light discovered that the statue of the Nepto Dragon was missing one of its eyes, a glimmering jewel. The Warriors shrank themselves to enter a passage in the statue's mouth, and soon found the Giant Rat responsible for the jewel's theft. They defeated the rat and replaced the jewel in the statue, thereby calming the Nepto Dragon who entrusted them with the Fang of Water before returning to its slumber.", 
            "epilogue_image_path": "/dff/static/lang/image/dungeon/203004_epilogue.png", 
            "name": "Nepto Temple", 
            "bgm": "bgm_03_013", 
            "prologue": "The once peaceful town of Vikings' Cove has faced numerous attacks by the Nepto Dragon, which has grown violent of late. A pall lies over the village, and the Warriors of Light venture to the Nepto Temple to seek out answers.", 
            "is_master": false, 
            "prologue_image_path": "/dff/static/lang/image/dungeon/203004_prologue.png"
        }, 
        {
            "background_image_path": "/dff/static/lang/image/dungeon/403008_bg.png", 
            "order_no": 1, 
            "captures": [
                {
                    "sp_scores": [
                        {
                            "title": "Defeat Hein without being KO'd.", 
                            "battle_id": 503034
                        }, 
                        {
                            "title": "Win without the Black Mage being KO'd.", 
                            "battle_id": 503034
                        }
                    ], 
                    "image_path": "/dff/static/lang/image/enemy/403008.png", 
                    "tip_battle": {
                        "message": "Hein has extremely high evasion, so it's really <span class=\"red\">hard to land a physical attack</span> on him, kupo! Not only that, every 3 turns he uses <span class=\"red\">Barrier Shift</span> to change his elemental weakness. You'll need a whole suite of <span class=\"red\">fire, lightning, and ice magic</span> to bring him down!", 
                        "group_id": 410104, 
                        "id": 410104, 
                        "title": "Hein"
                    }
                }
            ], 
            "is_new": false, 
            "rank": 0, 
            "closed_at": 2145938400, 
            "id": 403008, 
            "is_clear": false, 
            "button_style": "NORMAL", 
            "opened_at": 1434675600, 
            "world_id": 103001, 
            "type": 2, 
            "challenge_level": 80, 
            "is_unlocked": false, 
            "series_id": 103001, 
            "prizes": {
                "1": [
                    {
                        "id": 92000000, 
                        "type_name": "COMMON", 
                        "num": 14000, 
                        "image_path": "/dff/static/lang/image/common_item/92000000.png", 
                        "name": "Gil"
                    }
                ], 
                "3": [
                    {
                        "id": 24098004, 
                        "type_name": "EQUIPMENT", 
                        "num": 1, 
                        "image_path": "/dff/static/lang/image/equipment/24098004/24098004_04_112.png", 
                        "name": "Large Scarletite"
                    }, 
                    {
                        "id": 94000000, 
                        "type_name": "COMMON", 
                        "num": 1, 
                        "image_path": "/dff/static/lang/image/common_item/94000000.png", 
                        "name": "Stamina Shard"
                    }
                ], 
                "2": [
                    {
                        "id": 101040030, 
                        "type_name": "MEMORY_CRYSTAL", 
                        "num": 1, 
                        "image_path": "/dff/static/lang/image/memory_crystal/101040030/101040030_112.png", 
                        "name": "Kain Memory Crystal"
                    }, 
                    {
                        "id": 91000000, 
                        "type_name": "COMMON", 
                        "num": 1, 
                        "image_path": "/dff/static/lang/image/common_item/91000000.png", 
                        "name": "Mythril"
                    }
                ]
            }, 
            "total_stamina": 52, 
            "epilogue": "The evil wizard Hein had been using King Argus's soldiers to further his plans for world domination. The party made their way to the throne at the top of Castle Hein where they found the wizard himself, a skeletal creature descended into darkness. Though Hein's Barrier Shift made victory no certain thing, the Warriors of Light prevailed, lifting the curse on the Elder Tree of the Living Woods.", 
            "epilogue_image_path": "/dff/static/lang/image/dungeon/403008_epilogue.png", 
            "name": "Hein's Castle", 
            "bgm": "bgm_03_021", 
            "prologue": "The Warriors of Light are taken captive in Tokkul and thrown in the dungeons of Castle Hein. Now they must free themselves and put an end to Hein's evil schemes.", 
            "is_master": false, 
            "prologue_image_path": "/dff/static/lang/image/dungeon/403008_prologue.png"
        }, 
        {
            "background_image_path": "/dff/static/lang/image/dungeon/203001_bg.png", 
            "order_no": 1, 
            "captures": [
                {
                    "sp_scores": [
                        {
                            "title": "Defeat the Great Tortoise without being KO'd.", 
                            "battle_id": 303004
                        }
                    ], 
                    "image_path": "/dff/static/lang/image/enemy/403001.png", 
                    "tip_battle": {
                        "message": "The Great Tortoise has <span class=\"red\">lots of health</span> and no real vulnerabilities, so use abilities like <span class=\"red\">Armor Break and Mental Break</span> to wear down its defenses, kupo!", 
                        "group_id": 420079, 
                        "id": 410079, 
                        "title": "Great Tortoise"
                    }
                }
            ], 
            "is_new": false, 
            "rank": 3, 
            "closed_at": 2145938400, 
            "id": 203001, 
            "is_clear": true, 
            "button_style": "NORMAL", 
            "opened_at": 1424152800, 
            "world_id": 103001, 
            "type": 1, 
            "challenge_level": 35, 
            "is_unlocked": true, 
            "series_id": 103001, 
            "prizes": {
                "1": [
                    {
                        "id": 92000000, 
                        "type_name": "COMMON", 
                        "num": 3000, 
                        "image_path": "/dff/static/lang/image/common_item/92000000.png", 
                        "name": "Gil"
                    }
                ], 
                "3": [
                    {
                        "id": 40000038, 
                        "type_name": "ABILITY_MATERIAL", 
                        "num": 3, 
                        "image_path": "/dff/static/lang/image/ability_material/40000038/40000038_112.png", 
                        "name": "Ice Orb"
                    }, 
                    {
                        "id": 94000000, 
                        "type_name": "COMMON", 
                        "num": 1, 
                        "image_path": "/dff/static/lang/image/common_item/94000000.png", 
                        "name": "Stamina Shard"
                    }
                ], 
                "2": [
                    {
                        "id": 10300100, 
                        "type_name": "BUDDY", 
                        "num": 1, 
                        "image_path": "/dff/static/lang/image/buddy/10300100/10300100.png", 
                        "name": "Luneth"
                    }, 
                    {
                        "id": 94000000, 
                        "type_name": "COMMON", 
                        "num": 1, 
                        "image_path": "/dff/static/lang/image/common_item/94000000.png", 
                        "name": "Stamina Shard"
                    }
                ]
            }, 
            "total_stamina": 37, 
            "epilogue": "Having survived goblin attacks and battle with the Great Tortoise, Luneth finally made his way to the altar of the Wind Crystal. The crystal enveloped him in light, and in an instant, he understood what must be done. And so the newly anointed Warrior of Light set out to drive back the darkness and restore light to the world.", 
            "epilogue_image_path": "/dff/static/lang/image/dungeon/203001_epilogue.png", 
            "name": "Altar Cave", 
            "bgm": "bgm_03_002", 
            "prologue": "A young adventurer has wandered deep into the Altar Cave opened in the great earthquake. The epic journey of the Warriors of Light begins here...", 
            "is_master": true, 
            "prologue_image_path": "/dff/static/lang/image/dungeon/203001_prologue.png"
        }, 
        {
            "background_image_path": "/dff/static/lang/image/dungeon/203005_bg.png", 
            "order_no": 1, 
            "captures": [
                {
                    "sp_scores": [
                        {
                            "title": "Defeat Medusa without being KO'd.", 
                            "battle_id": 303022
                        }
                    ], 
                    "image_path": "/dff/static/lang/image/enemy/403005.png", 
                    "tip_battle": {
                        "message": "Medusa's <span class=\"red\">Gaze</span> can turn a character to stone, kupo! Have <span class=\"red\">Stona and Esuna</span> at the ready to cure your party! Studying Medusa's myth may give some clues to defeating her...", 
                        "group_id": 410101, 
                        "id": 410101, 
                        "title": "Medusa"
                    }
                }
            ], 
            "is_new": false, 
            "rank": 0, 
            "closed_at": 2145938400, 
            "id": 203005, 
            "is_clear": false, 
            "button_style": "NORMAL", 
            "opened_at": 1434675600, 
            "world_id": 103001, 
            "type": 1, 
            "challenge_level": 45, 
            "is_unlocked": false, 
            "series_id": 103001, 
            "prizes": {
                "1": [
                    {
                        "id": 92000000, 
                        "type_name": "COMMON", 
                        "num": 4000, 
                        "image_path": "/dff/static/lang/image/common_item/92000000.png", 
                        "name": "Gil"
                    }
                ], 
                "3": [
                    {
                        "id": 40000048, 
                        "type_name": "ABILITY_MATERIAL", 
                        "num": 3, 
                        "image_path": "/dff/static/lang/image/ability_material/40000048/40000048_112.png", 
                        "name": "Earth Orb"
                    }, 
                    {
                        "id": 24099003, 
                        "type_name": "EQUIPMENT", 
                        "num": 1, 
                        "image_path": "/dff/static/lang/image/equipment/24099003/24099003_03_112.png", 
                        "name": "Adamantite"
                    }
                ], 
                "2": [
                    {
                        "id": 10300200, 
                        "type_name": "BUDDY", 
                        "num": 1, 
                        "image_path": "/dff/static/lang/image/buddy/10300200/10300200.png", 
                        "name": "Arc"
                    }, 
                    {
                        "id": 94000000, 
                        "type_name": "COMMON", 
                        "num": 1, 
                        "image_path": "/dff/static/lang/image/common_item/94000000.png", 
                        "name": "Stamina Shard"
                    }
                ]
            }, 
            "total_stamina": 61, 
            "epilogue": "In the Tower of Owen, the Warriors of Light found Medusa trying to destroy the tower and send the Floating Continent crashing down. Though they were successful in stopping her, the tower was damaged and might have failed had Desch's memories not returned. Realizing he was one of the Ancients and the Guardian of the Tower, he risked his life to fix the tower furnace. Thanks to his bravery, the tower was saved and the maelstrom blocking passage to the north subsided, allowing the Warriors of Light to once again take to the seas.", 
            "epilogue_image_path": "/dff/static/lang/image/dungeon/203005_epilogue.png", 
            "name": "Tower of Owen", 
            "bgm": "bgm_03_019", 
            "prologue": "From the Gulgan's prophecy, the Warriors of Light have learned of the Tower of Owen, and now Desch is slowly regaining his memory, aiding their passage through the tower.", 
            "is_master": false, 
            "prologue_image_path": "/dff/static/lang/image/dungeon/203005_prologue.png"
        }, 
        {
            "background_image_path": "/dff/static/lang/image/dungeon/403001_bg.png", 
            "order_no": 1, 
            "captures": [
                {
                    "sp_scores": [
                        {
                            "title": "Defeat the Great Tortoise without being KO'd.", 
                            "battle_id": 503004
                        }
                    ], 
                    "image_path": "/dff/static/lang/image/enemy/403001.png", 
                    "tip_battle": {
                        "message": "The Great Tortoise has <span class=\"red\">lots of health</span> and no real vulnerabilities, so use abilities like <span class=\"red\">Armor Break and Mental Break</span> to wear down its defenses, kupo!", 
                        "group_id": 420079, 
                        "id": 410079, 
                        "title": "Great Tortoise"
                    }
                }
            ], 
            "is_new": true, 
            "rank": 0, 
            "closed_at": 2145938400, 
            "id": 403001, 
            "is_clear": false, 
            "button_style": "NORMAL", 
            "opened_at": 1424152800, 
            "world_id": 103001, 
            "type": 2, 
            "challenge_level": 55, 
            "is_unlocked": true, 
            "series_id": 103001, 
            "prizes": {
                "1": [
                    {
                        "id": 92000000, 
                        "type_name": "COMMON", 
                        "num": 12000, 
                        "image_path": "/dff/static/lang/image/common_item/92000000.png", 
                        "name": "Gil"
                    }
                ], 
                "3": [
                    {
                        "id": 40000009, 
                        "type_name": "ABILITY_MATERIAL", 
                        "num": 3, 
                        "image_path": "/dff/static/lang/image/ability_material/40000009/40000009_112.png", 
                        "name": "Greater White Orb"
                    }, 
                    {
                        "id": 94000000, 
                        "type_name": "COMMON", 
                        "num": 1, 
                        "image_path": "/dff/static/lang/image/common_item/94000000.png", 
                        "name": "Stamina Shard"
                    }
                ], 
                "2": [
                    {
                        "id": 94000000, 
                        "type_name": "COMMON", 
                        "num": 1, 
                        "image_path": "/dff/static/lang/image/common_item/94000000.png", 
                        "name": "Stamina Shard"
                    }, 
                    {
                        "id": 91000000, 
                        "type_name": "COMMON", 
                        "num": 1, 
                        "image_path": "/dff/static/lang/image/common_item/91000000.png", 
                        "name": "Mythril"
                    }
                ]
            }, 
            "total_stamina": 57, 
            "epilogue": "Having survived goblin attacks and battle with the Great Tortoise, Luneth finally made his way to the altar of the Wind Crystal. The crystal enveloped him in light, and in an instant, he understood what must be done. And so the newly anointed Warrior of Light set out to drive back the darkness and restore light to the world.", 
            "epilogue_image_path": "/dff/static/lang/image/dungeon/403001_epilogue.png", 
            "name": "Altar Cave", 
            "bgm": "bgm_03_002", 
            "prologue": "A young adventurer has wandered deep into the Altar Cave opened in the great earthquake. The epic journey of the Warriors of Light begins here...", 
            "is_master": false, 
            "prologue_image_path": "/dff/static/lang/image/dungeon/403001_prologue.png"
        }
    ], 
    "user": {
        "max_stamina": 66, 
        "stamina_recovery_remaining_time": 0, 
        "stamina_recovery_time": 180, 
        "supporter_ss_gauge": 2, 
        "id": 5143210343006208, 
        "can_review": true, 
        "func_tutorial_bits": 491517, 
        "max_follower_num": 100, 
        "stamina": 66, 
        "gil": 218067, 
        "start_time_of_today": 1439384400, 
        "release_id": 0, 
        "residual_stamina_piece": 0, 
        "is_in_dungeon": false, 
        "last_logined_at": 1439386661, 
        "soul_piece": 52, 
        "followee_num": 27, 
        "max_followee_num": 100, 
        "dungeon_id": 0, 
        "name": "Tyro", 
        "is_update_last_logined_at": false, 
        "stamina_piece": 330, 
        "tutorial_step": 255, 
        "has_all_clear_ver_to_show": false
    }, 
    "world": {
        "kept_out_at": 2062803599, 
        "image_path": "/dff/static/lang/image/world/103001.png", 
        "name": "FF III", 
        "bgm": "bgm_03_007", 
        "is_unlocked": true, 
        "series_id": 103001, 
        "opened_at": 1431651600, 
        "series_formal_name": "FINAL FANTASY III", 
        "has_new_dungeon": false, 
        "closed_at": 2063066399, 
        "type": 1, 
        "id": 103001, 
        "door_image_path": "/dff/static/lang/image/world/103001_door.png"
    }
}
