{
    "SERVER_TIME": 1434425966, 
    "battles": [
        {
            "dungeon_id": 204005, 
            "has_boss": 0, 
            "id": 304015, 
            "is_unlocked": true, 
            "name": "Fabul Castle - 1st Battle", 
            "order_no": 1, 
            "round_num": 1, 
            "stamina": 1
        }, 
        {
            "dungeon_id": 204005, 
            "has_boss": 0, 
            "id": 304016, 
            "is_unlocked": true, 
            "name": "Fabul Castle - 2nd Battle", 
            "order_no": 1, 
            "round_num": 1, 
            "stamina": 1
        }, 
        {
            "dungeon_id": 204005, 
            "has_boss": 0, 
            "id": 304017, 
            "is_unlocked": true, 
            "name": "Fabul Castle - 3rd Battle", 
            "order_no": 1, 
            "round_num": 1, 
            "stamina": 1
        }, 
        {
            "dungeon_id": 204005, 
            "has_boss": 0, 
            "id": 304018, 
            "is_unlocked": true, 
            "name": "Fabul Castle - 4th Battle", 
            "order_no": 1, 
            "round_num": 1, 
            "stamina": 1
        }, 
        {
            "dungeon_id": 204005, 
            "has_boss": 0, 
            "id": 304019, 
            "is_unlocked": true, 
            "name": "Fabul Castle - 5th Battle", 
            "order_no": 1, 
            "round_num": 1, 
            "stamina": 1
        }, 
        {
            "dungeon_id": 204005, 
            "has_boss": 0, 
            "id": 304020, 
            "is_unlocked": true, 
            "name": "Fabul Castle - 6th Battle", 
            "order_no": 1, 
            "round_num": 1, 
            "stamina": 1
        }, 
        {
            "dungeon_id": 204005, 
            "has_boss": 1, 
            "id": 304021, 
            "is_unlocked": true, 
            "name": "Fabul Castle - Final Battle", 
            "order_no": 1, 
            "round_num": 1, 
            "stamina": 2
        }
    ], 
    "dungeon_session": {
        "background_image_path": "/dff/static/lang/image/dungeon/204005_bg.png", 
        "battle_id": 304015, 
        "bgm": "bgm_04_020", 
        "challenge_level": 8, 
        "closed_at": 2145938400, 
        "dungeon_id": 204005, 
        "kept_out_at": 2145938400, 
        "max_supporter_ss_gauge": 2, 
        "name": "Fabul Castle", 
        "opened_at": 1398924000, 
        "order_no": 1, 
        "party_status": {
            "1": {
                "ability_1_num": 6, 
                "ability_2_num": 8, 
                "hp": 3679, 
                "no": 1, 
                "soul_strike_gauge": 0, 
                "status_ailments": [], 
                "user_buddy_id": 7215898
            }, 
            "2": {
                "ability_1_num": 4, 
                "ability_2_num": 4, 
                "hp": 4574, 
                "no": 2, 
                "soul_strike_gauge": 0, 
                "status_ailments": [], 
                "user_buddy_id": 12661732
            }, 
            "3": {
                "ability_1_num": 6, 
                "ability_2_num": 4, 
                "hp": 3883, 
                "no": 3, 
                "soul_strike_gauge": 0, 
                "status_ailments": [], 
                "user_buddy_id": 7266620
            }, 
            "4": {
                "ability_1_num": 6, 
                "ability_2_num": 4, 
                "hp": 2963, 
                "no": 4, 
                "soul_strike_gauge": 0, 
                "status_ailments": [], 
                "user_buddy_id": 13158429
            }, 
            "5": {
                "ability_1_num": 2, 
                "ability_2_num": 10, 
                "hp": 3419, 
                "no": 5, 
                "soul_strike_gauge": 0, 
                "status_ailments": [], 
                "user_buddy_id": 13180327
            }
        }, 
        "series_id": 104001, 
        "supporter_ss_gauge": 2, 
        "type": 1, 
        "world_id": 104001
    }, 
    "fellow_session": {
        "can_follow": false, 
        "can_remake_fellow_list": false, 
        "fellow_profile": {
            "last_logged_in_at": 0, 
            "lead_buddy_acc": 118, 
            "lead_buddy_accessory_id": 241808435, 
            "lead_buddy_accessory_image_path": "/dff/static/lang/image/equipment/23080074/23080074_04_112.png", 
            "lead_buddy_accessory_level": 1, 
            "lead_buddy_accessory_max_level": 1, 
            "lead_buddy_accessory_name": "Magic Armlet (IX)", 
            "lead_buddy_accessory_series_id": 109001, 
            "lead_buddy_armor_id": 240432165, 
            "lead_buddy_armor_image_path": "/dff/static/lang/image/equipment/22055026/22055026_05_112.png", 
            "lead_buddy_armor_level": 20, 
            "lead_buddy_armor_max_level": 20, 
            "lead_buddy_armor_name": "Black Robe (IX)", 
            "lead_buddy_armor_series_id": 109001, 
            "lead_buddy_atk": 110, 
            "lead_buddy_def": 143, 
            "lead_buddy_eva": 128, 
            "lead_buddy_hp": 3883, 
            "lead_buddy_id": 10900200, 
            "lead_buddy_image_path": "/dff/static/lang/image/buddy/10900200/10900200.png", 
            "lead_buddy_job_name": "Summoner", 
            "lead_buddy_level": 65, 
            "lead_buddy_matk": 288, 
            "lead_buddy_mdef": 247, 
            "lead_buddy_mnd": 239, 
            "lead_buddy_series_acc": 118, 
            "lead_buddy_series_atk": 110, 
            "lead_buddy_series_def": 143, 
            "lead_buddy_series_eva": 128, 
            "lead_buddy_series_hp": 3883, 
            "lead_buddy_series_id": 109001, 
            "lead_buddy_series_matk": 288, 
            "lead_buddy_series_mdef": 247, 
            "lead_buddy_series_mnd": 239, 
            "lead_buddy_series_spd": 127, 
            "lead_buddy_soul_strike_consume_ss_gauge": 1, 
            "lead_buddy_soul_strike_description": "Summon Ramuh, dealing heavy magic lightning damage to all targets.", 
            "lead_buddy_soul_strike_equipment_image_path": "/dff/static/lang/image/equipment/21009031/21009031_05_112.png", 
            "lead_buddy_soul_strike_equipment_series_id": 109001, 
            "lead_buddy_soul_strike_id": 20360002, 
            "lead_buddy_soul_strike_image_path": "/dff/static/lang/image/soulstrike/20360002/20360002_256.png", 
            "lead_buddy_soul_strike_name": "Ramuh", 
            "lead_buddy_spd": 127, 
            "lead_buddy_weapon_id": 240402240, 
            "lead_buddy_weapon_image_path": "/dff/static/lang/image/equipment/21009031/21009031_05_112.png", 
            "lead_buddy_weapon_level": 20, 
            "lead_buddy_weapon_max_level": 20, 
            "lead_buddy_weapon_name": "Storm Staff (IX)", 
            "lead_buddy_weapon_series_id": 109001, 
            "nickname": "Guardian", 
            "profile_message": "Ohai :)", 
            "user_id": 6477038152056832, 
            "via_battle": true
        }, 
        "has_fellow": true, 
        "status": 1
    }, 
    "multi_party": {
        "current_deck_no": 1, 
        "parties": [
            {
                "deck_no": 1, 
                "slot_to_row": {
                    "1": 1, 
                    "2": 1, 
                    "3": 2, 
                    "4": 2, 
                    "5": 2
                }, 
                "slot_to_user_buddy_id": {
                    "1": 7215898, 
                    "2": 12661732, 
                    "3": 7266620, 
                    "4": 13158429, 
                    "5": 13180327
                }
            }, 
            {
                "deck_no": 2, 
                "slot_to_row": {}, 
                "slot_to_user_buddy_id": {}
            }, 
            {
                "deck_no": 3, 
                "slot_to_row": {}, 
                "slot_to_user_buddy_id": {}
            }, 
            {
                "deck_no": 4, 
                "slot_to_row": {}, 
                "slot_to_user_buddy_id": {}
            }, 
            {
                "deck_no": 5, 
                "slot_to_row": {}, 
                "slot_to_user_buddy_id": {}
            }
        ]
    }, 
    "success": true, 
    "user": {
        "can_review": true, 
        "dungeon_id": 204005, 
        "followee_num": 44, 
        "func_tutorial_bits": 131071, 
        "gil": 3841861, 
        "has_all_clear_ver_to_show": false, 
        "id": 5570609408901120, 
        "is_in_dungeon": true, 
        "is_update_last_logined_at": false, 
        "last_logined_at": 1434373227, 
        "max_followee_num": 100, 
        "max_follower_num": 100, 
        "max_stamina": 101, 
        "name": "MDB", 
        "release_id": 0, 
        "residual_stamina_piece": 0, 
        "soul_piece": 46, 
        "stamina": 91, 
        "stamina_piece": 505, 
        "stamina_recovery_remaining_time": 1726, 
        "stamina_recovery_time": 180, 
        "start_time_of_today": 1434373200, 
        "supporter_ss_gauge": 2, 
        "tutorial_step": 255
    }, 
    "user_dungeon": {
        "background_image_path": "/dff/static/lang/image/dungeon/204005_bg.png", 
        "bgm": "bgm_04_020", 
        "button_style": "NORMAL", 
        "captures": [
            {
                "image_path": "/dff/static/lang/image/enemy/404030.png", 
                "sp_scores": [
                    {
                        "battle_id": 304021, 
                        "title": "Defeat the Dragoon without being KO'd."
                    }
                ], 
                "tip_battle": {
                    "group_id": 420005, 
                    "id": 410005, 
                    "message": "Kain's <span class=\"red\">Jump</span> ability hits hard, kupo. After it lands, be ready to <span class=\"red\">heal up right away</span>, or it won't be pretty. Oh my, no...", 
                    "title": "Kain"
                }
            }
        ], 
        "challenge_level": 8, 
        "closed_at": 2145938400, 
        "epilogue": "Together with Yang, Cecil and the party defend Fabul Castle from the forces of Baron. Yet the monsters that Golbez employs prove too much for the heroes to handle, and they are pushed back to the Crystal Chamber. There, the commander of the assault reveals himself to be Cecil's friend Kain. The bewildered Cecil is powerless to resist as Kain and Golbez walk off with Rosa and the crystal.", 
        "epilogue_image_path": "/dff/static/lang/image/dungeon/204005_epilogue.png", 
        "id": 204005, 
        "is_clear": true, 
        "is_master": true, 
        "is_new": false, 
        "is_unlocked": true, 
        "name": "Fabul Castle", 
        "opened_at": 1398924000, 
        "order_no": 1, 
        "prizes": {
            "1": [
                {
                    "id": 92000000, 
                    "image_path": "/dff/static/lang/image/common_item/92000000.png", 
                    "name": "Gil", 
                    "num": 700, 
                    "type_name": "COMMON"
                }
            ], 
            "2": [
                {
                    "id": 10400400, 
                    "image_path": "/dff/static/lang/image/buddy/10400400/10400400.png", 
                    "name": "Rydia", 
                    "num": 1, 
                    "type_name": "BUDDY"
                }, 
                {
                    "id": 91000000, 
                    "image_path": "/dff/static/lang/image/common_item/91000000.png", 
                    "name": "Mythril", 
                    "num": 1, 
                    "type_name": "COMMON"
                }
            ], 
            "3": [
                {
                    "id": 40000041, 
                    "image_path": "/dff/static/lang/image/ability_material/40000041/40000041_112.png", 
                    "name": "Minor Lightning Orb", 
                    "num": 5, 
                    "type_name": "ABILITY_MATERIAL"
                }, 
                {
                    "id": 94000000, 
                    "image_path": "/dff/static/lang/image/common_item/94000000.png", 
                    "name": "Stamina Shard", 
                    "num": 1, 
                    "type_name": "COMMON"
                }
            ]
        }, 
        "prologue": "Its monk warriors decimated, Fabul is in dire straits. Cecil and Edward come to stand with Yang against the forces of Baron.", 
        "prologue_image_path": "/dff/static/lang/image/dungeon/204005_prologue.png", 
        "rank": 3, 
        "series_id": 104001, 
        "total_stamina": 8, 
        "type": 1, 
        "world_id": 104001
    }
}
