{
    "SERVER_TIME": 1437265055, 
    "detailed_fellows": [
        {
            "is_new_relation": false, 
            "last_logged_in_at": 1437264631, 
            "lead_buddy_acc": 114, 
            "lead_buddy_accessory_id": 47913351, 
            "lead_buddy_accessory_image_path": "/dff/static/lang/image/equipment/23080001/23080001_01_112.png", 
            "lead_buddy_accessory_level": 1, 
            "lead_buddy_accessory_max_level": 1, 
            "lead_buddy_accessory_name": "Power Wrist (VII)", 
            "lead_buddy_accessory_series_id": 107001, 
            "lead_buddy_armor_id": 64549205, 
            "lead_buddy_armor_image_path": "/dff/static/lang/image/equipment/22054008/22054008_03_112.png", 
            "lead_buddy_armor_level": 10, 
            "lead_buddy_armor_max_level": 10, 
            "lead_buddy_armor_name": "Knight Armor (III)", 
            "lead_buddy_armor_series_id": 103001, 
            "lead_buddy_atk": 105, 
            "lead_buddy_def": 90, 
            "lead_buddy_eva": 120, 
            "lead_buddy_hp": 1915, 
            "lead_buddy_id": 11000300, 
            "lead_buddy_image_path": "/dff/static/lang/image/buddy/11000300/11000300.png", 
            "lead_buddy_job_name": "Guardian", 
            "lead_buddy_level": 31, 
            "lead_buddy_matk": 45, 
            "lead_buddy_mdef": 64, 
            "lead_buddy_mnd": 51, 
            "lead_buddy_series_acc": 114, 
            "lead_buddy_series_atk": 108, 
            "lead_buddy_series_def": 90, 
            "lead_buddy_series_eva": 120, 
            "lead_buddy_series_hp": 1915, 
            "lead_buddy_series_id": 110001, 
            "lead_buddy_series_matk": 45, 
            "lead_buddy_series_mdef": 64, 
            "lead_buddy_series_mnd": 51, 
            "lead_buddy_series_spd": 109, 
            "lead_buddy_soul_strike_consume_ss_gauge": 1, 
            "lead_buddy_soul_strike_description": "Deal water elemental damage to all targets.", 
            "lead_buddy_soul_strike_equipment_image_path": "", 
            "lead_buddy_soul_strike_equipment_series_id": 0, 
            "lead_buddy_soul_strike_id": 20150001, 
            "lead_buddy_soul_strike_image_path": "/dff/static/lang/image/soulstrike/20150001/20150001_256.png", 
            "lead_buddy_soul_strike_name": "Element Reels", 
            "lead_buddy_spd": 109, 
            "lead_buddy_weapon_id": 64549208, 
            "lead_buddy_weapon_image_path": "/dff/static/lang/image/equipment/21001011/21001011_04_112.png", 
            "lead_buddy_weapon_level": 15, 
            "lead_buddy_weapon_max_level": 15, 
            "lead_buddy_weapon_name": "Avenger (XII)\uff0b", 
            "lead_buddy_weapon_series_id": 112001, 
            "nickname": "Ashley", 
            "profile_message": "Hello there!", 
            "relation_status": 2, 
            "relation_updated_at": 1437202607, 
            "user_id": 5256916976533504, 
            "via_battle": false
        }, 
        {
            "is_new_relation": false, 
            "last_logged_in_at": 1437119241, 
            "lead_buddy_acc": 116, 
            "lead_buddy_accessory_id": 107696409, 
            "lead_buddy_accessory_image_path": "/dff/static/lang/image/equipment/23080020/23080020_03_112.png", 
            "lead_buddy_accessory_level": 1, 
            "lead_buddy_accessory_max_level": 1, 
            "lead_buddy_accessory_name": "Hero's Ring (VI)", 
            "lead_buddy_accessory_series_id": 106001, 
            "lead_buddy_armor_id": 21065050, 
            "lead_buddy_armor_image_path": "/dff/static/lang/image/equipment/22051011/22051011_05_112.png", 
            "lead_buddy_armor_level": 20, 
            "lead_buddy_armor_max_level": 20, 
            "lead_buddy_armor_name": "Royal Crown (VI)\uff0b", 
            "lead_buddy_armor_series_id": 106001, 
            "lead_buddy_atk": 146, 
            "lead_buddy_def": 80, 
            "lead_buddy_eva": 124, 
            "lead_buddy_hp": 2449, 
            "lead_buddy_id": 10600100, 
            "lead_buddy_image_path": "/dff/static/lang/image/buddy/10600100/10600100.png", 
            "lead_buddy_job_name": "Magitek Elite", 
            "lead_buddy_level": 36, 
            "lead_buddy_matk": 225, 
            "lead_buddy_mdef": 149, 
            "lead_buddy_mnd": 73, 
            "lead_buddy_series_acc": 116, 
            "lead_buddy_series_atk": 146, 
            "lead_buddy_series_def": 80, 
            "lead_buddy_series_eva": 124, 
            "lead_buddy_series_hp": 2449, 
            "lead_buddy_series_id": 106001, 
            "lead_buddy_series_matk": 225, 
            "lead_buddy_series_mdef": 149, 
            "lead_buddy_series_mnd": 73, 
            "lead_buddy_series_spd": 109, 
            "lead_buddy_soul_strike_consume_ss_gauge": 1, 
            "lead_buddy_soul_strike_description": "Enter Trance and deal physical damage to one target.", 
            "lead_buddy_soul_strike_equipment_image_path": "", 
            "lead_buddy_soul_strike_equipment_series_id": 0, 
            "lead_buddy_soul_strike_id": 20100001, 
            "lead_buddy_soul_strike_image_path": "/dff/static/lang/image/soulstrike/20100001/20100001_256.png", 
            "lead_buddy_soul_strike_name": "Trance Attack", 
            "lead_buddy_spd": 109, 
            "lead_buddy_weapon_id": 105411534, 
            "lead_buddy_weapon_image_path": "/dff/static/lang/image/equipment/21002039/21002039_05_112.png", 
            "lead_buddy_weapon_level": 20, 
            "lead_buddy_weapon_max_level": 20, 
            "lead_buddy_weapon_name": "Enhancer (VI)", 
            "lead_buddy_weapon_series_id": 106001, 
            "nickname": "Stukov", 
            "profile_message": "It's been a long day...", 
            "relation_status": 2, 
            "relation_updated_at": 1437096095, 
            "user_id": 6465629305438208, 
            "via_battle": false
        }, 
        {
            "is_new_relation": false, 
            "last_logged_in_at": 1437218366, 
            "lead_buddy_acc": 111, 
            "lead_buddy_accessory_id": 178447458, 
            "lead_buddy_accessory_image_path": "/dff/static/lang/image/equipment/23080021/23080021_03_112.png", 
            "lead_buddy_accessory_level": 1, 
            "lead_buddy_accessory_max_level": 1, 
            "lead_buddy_accessory_name": "Angel Ring (V)", 
            "lead_buddy_accessory_series_id": 105001, 
            "lead_buddy_armor_id": 173608936, 
            "lead_buddy_armor_image_path": "/dff/static/lang/image/equipment/22051011/22051011_05_112.png", 
            "lead_buddy_armor_level": 20, 
            "lead_buddy_armor_max_level": 20, 
            "lead_buddy_armor_name": "Royal Crown (VI)\uff0b", 
            "lead_buddy_armor_series_id": 106001, 
            "lead_buddy_atk": 82, 
            "lead_buddy_def": 89, 
            "lead_buddy_eva": 124, 
            "lead_buddy_hp": 2678, 
            "lead_buddy_id": 10500200, 
            "lead_buddy_image_path": "/dff/static/lang/image/buddy/10500200/10500200.png", 
            "lead_buddy_job_name": "Princess of Tycoon", 
            "lead_buddy_level": 50, 
            "lead_buddy_matk": 134, 
            "lead_buddy_mdef": 170, 
            "lead_buddy_mnd": 198, 
            "lead_buddy_series_acc": 111, 
            "lead_buddy_series_atk": 82, 
            "lead_buddy_series_def": 89, 
            "lead_buddy_series_eva": 124, 
            "lead_buddy_series_hp": 2678, 
            "lead_buddy_series_id": 105001, 
            "lead_buddy_series_matk": 134, 
            "lead_buddy_series_mdef": 170, 
            "lead_buddy_series_mnd": 198, 
            "lead_buddy_series_spd": 118, 
            "lead_buddy_soul_strike_consume_ss_gauge": 1, 
            "lead_buddy_soul_strike_description": "Grant Regen to all allies.", 
            "lead_buddy_soul_strike_equipment_image_path": "", 
            "lead_buddy_soul_strike_equipment_series_id": 0, 
            "lead_buddy_soul_strike_id": 20200001, 
            "lead_buddy_soul_strike_image_path": "/dff/static/lang/image/soulstrike/20200001/20200001_256.png", 
            "lead_buddy_soul_strike_name": "Mass Regen", 
            "lead_buddy_spd": 118, 
            "lead_buddy_weapon_id": 180962723, 
            "lead_buddy_weapon_image_path": "/dff/static/lang/image/equipment/21009016/21009016_04_112.png", 
            "lead_buddy_weapon_level": 15, 
            "lead_buddy_weapon_max_level": 15, 
            "lead_buddy_weapon_name": "Rune Staff (IV)\uff0b", 
            "lead_buddy_weapon_series_id": 104001, 
            "nickname": "Bailey", 
            "profile_message": "Hello there!", 
            "relation_status": 2, 
            "relation_updated_at": 1437100657, 
            "user_id": 4876100027023360, 
            "via_battle": false
        }, 
        {
            "is_new_relation": false, 
            "last_logged_in_at": 1437150696, 
            "lead_buddy_acc": 116, 
            "lead_buddy_accessory_id": 186030948, 
            "lead_buddy_accessory_image_path": "/dff/static/lang/image/equipment/23080019/23080019_03_112.png", 
            "lead_buddy_accessory_level": 1, 
            "lead_buddy_accessory_max_level": 1, 
            "lead_buddy_accessory_name": "Hyper Wrist (VI)", 
            "lead_buddy_accessory_series_id": 106001, 
            "lead_buddy_armor_id": 83314235, 
            "lead_buddy_armor_image_path": "/dff/static/lang/image/equipment/22052013/22052013_05_112.png", 
            "lead_buddy_armor_level": 13, 
            "lead_buddy_armor_max_level": 20, 
            "lead_buddy_armor_name": "Genji Helm (V)", 
            "lead_buddy_armor_series_id": 105001, 
            "lead_buddy_atk": 227, 
            "lead_buddy_def": 161, 
            "lead_buddy_eva": 127, 
            "lead_buddy_hp": 3123, 
            "lead_buddy_id": 10700100, 
            "lead_buddy_image_path": "/dff/static/lang/image/buddy/10700100/10700100.png", 
            "lead_buddy_job_name": "SOLDIER", 
            "lead_buddy_level": 41, 
            "lead_buddy_matk": 48, 
            "lead_buddy_mdef": 144, 
            "lead_buddy_mnd": 59, 
            "lead_buddy_series_acc": 117, 
            "lead_buddy_series_atk": 319, 
            "lead_buddy_series_def": 175, 
            "lead_buddy_series_eva": 127, 
            "lead_buddy_series_hp": 3739, 
            "lead_buddy_series_id": 107001, 
            "lead_buddy_series_matk": 59, 
            "lead_buddy_series_mdef": 158, 
            "lead_buddy_series_mnd": 73, 
            "lead_buddy_series_spd": 124, 
            "lead_buddy_soul_strike_consume_ss_gauge": 1, 
            "lead_buddy_soul_strike_description": "Unleash three rapid sword slashes.", 
            "lead_buddy_soul_strike_equipment_image_path": "", 
            "lead_buddy_soul_strike_equipment_series_id": 0, 
            "lead_buddy_soul_strike_id": 20110001, 
            "lead_buddy_soul_strike_image_path": "/dff/static/lang/image/soulstrike/20110001/20110001_256.png", 
            "lead_buddy_soul_strike_name": "Sonic Break", 
            "lead_buddy_spd": 118, 
            "lead_buddy_weapon_id": 42197065, 
            "lead_buddy_weapon_image_path": "/dff/static/lang/image/equipment/21003005/21003005_05_112.png", 
            "lead_buddy_weapon_level": 17, 
            "lead_buddy_weapon_max_level": 20, 
            "lead_buddy_weapon_name": "Masamune (VII)", 
            "lead_buddy_weapon_series_id": 107001, 
            "nickname": "Wojtek ", 
            "profile_message": "Hello there!", 
            "relation_status": 2, 
            "relation_updated_at": 1437106434, 
            "user_id": 4509760925728768, 
            "via_battle": false
        }, 
        {
            "is_new_relation": false, 
            "last_logged_in_at": 1437260385, 
            "lead_buddy_acc": 116, 
            "lead_buddy_accessory_id": 174596590, 
            "lead_buddy_accessory_image_path": "/dff/static/lang/image/equipment/23080001/23080001_01_112.png", 
            "lead_buddy_accessory_level": 1, 
            "lead_buddy_accessory_max_level": 1, 
            "lead_buddy_accessory_name": "Power Wrist (VII)", 
            "lead_buddy_accessory_series_id": 107001, 
            "lead_buddy_armor_id": 297577217, 
            "lead_buddy_armor_image_path": "/dff/static/lang/image/equipment/22050028/22050028_06_112.png", 
            "lead_buddy_armor_level": 25, 
            "lead_buddy_armor_max_level": 25, 
            "lead_buddy_armor_name": "Kaiser Shield (XII)\uff0b", 
            "lead_buddy_armor_series_id": 112001, 
            "lead_buddy_atk": 207, 
            "lead_buddy_def": 181, 
            "lead_buddy_eva": 127, 
            "lead_buddy_hp": 3310, 
            "lead_buddy_id": 10700100, 
            "lead_buddy_image_path": "/dff/static/lang/image/buddy/10700100/10700100.png", 
            "lead_buddy_job_name": "SOLDIER", 
            "lead_buddy_level": 44, 
            "lead_buddy_matk": 51, 
            "lead_buddy_mdef": 137, 
            "lead_buddy_mnd": 63, 
            "lead_buddy_series_acc": 117, 
            "lead_buddy_series_atk": 230, 
            "lead_buddy_series_def": 195, 
            "lead_buddy_series_eva": 127, 
            "lead_buddy_series_hp": 3921, 
            "lead_buddy_series_id": 107001, 
            "lead_buddy_series_matk": 63, 
            "lead_buddy_series_mdef": 152, 
            "lead_buddy_series_mnd": 78, 
            "lead_buddy_series_spd": 125, 
            "lead_buddy_soul_strike_consume_ss_gauge": 1, 
            "lead_buddy_soul_strike_description": "Give the party Protect.", 
            "lead_buddy_soul_strike_equipment_image_path": "/dff/static/lang/image/equipment/22050028/22050028_06_112.png", 
            "lead_buddy_soul_strike_equipment_series_id": 112001, 
            "lead_buddy_soul_strike_id": 21000006, 
            "lead_buddy_soul_strike_image_path": "/dff/static/lang/image/soulstrike/21000006/21000006_256.png", 
            "lead_buddy_soul_strike_name": "Veil of Protection", 
            "lead_buddy_spd": 120, 
            "lead_buddy_weapon_id": 237894831, 
            "lead_buddy_weapon_image_path": "/dff/static/lang/image/equipment/21002033/21002033_05_112.png", 
            "lead_buddy_weapon_level": 20, 
            "lead_buddy_weapon_max_level": 20, 
            "lead_buddy_weapon_name": "Zantetsuken (VI)", 
            "lead_buddy_weapon_series_id": 106001, 
            "nickname": "Smiley", 
            "profile_message": "Spoon!!!", 
            "relation_status": 2, 
            "relation_updated_at": 1437205954, 
            "user_id": 4537402009845760, 
            "via_battle": false
        }
    ], 
    "fellow_listing_user_ids": [
        {
            "user_id": 5256916976533504
        }, 
        {
            "user_id": 6465629305438208
        }, 
        {
            "user_id": 4876100027023360
        }, 
        {
            "user_id": 4509760925728768
        }, 
        {
            "user_id": 4537402009845760
        }, 
        {
            "user_id": 5615751645888512
        }, 
        {
            "user_id": 5193126427754496
        }, 
        {
            "user_id": 4832155108638720
        }, 
        {
            "user_id": 5154348057231360
        }, 
        {
            "user_id": 5085064002011136
        }
    ], 
    "success": true
}
