{
    "SERVER_TIME": 1437282781, 
    "success": true, 
    "target_profiles": [
        {
            "is_new_relation": false, 
            "last_logged_in_at": 1437280597, 
            "lead_buddy_acc": 114, 
            "lead_buddy_accessory_id": 200856186, 
            "lead_buddy_accessory_image_path": "/dff/static/lang/image/equipment/23080001/23080001_01_112.png", 
            "lead_buddy_accessory_level": 1, 
            "lead_buddy_accessory_max_level": 1, 
            "lead_buddy_accessory_name": "Power Wrist (VII)", 
            "lead_buddy_accessory_series_id": 107001, 
            "lead_buddy_armor_id": 254114213, 
            "lead_buddy_armor_image_path": "/dff/static/lang/image/equipment/22053015/22053015_04_112.png", 
            "lead_buddy_armor_level": 15, 
            "lead_buddy_armor_max_level": 15, 
            "lead_buddy_armor_name": "Red Jacket (VI)", 
            "lead_buddy_armor_series_id": 106001, 
            "lead_buddy_atk": 201, 
            "lead_buddy_def": 150, 
            "lead_buddy_eva": 124, 
            "lead_buddy_hp": 4113, 
            "lead_buddy_id": 10701000, 
            "lead_buddy_image_path": "/dff/static/lang/image/buddy/10701000/10701000.png", 
            "lead_buddy_job_name": "SOLDIER", 
            "lead_buddy_level": 51, 
            "lead_buddy_matk": 75, 
            "lead_buddy_mdef": 142, 
            "lead_buddy_mnd": 75, 
            "lead_buddy_series_acc": 114, 
            "lead_buddy_series_atk": 201, 
            "lead_buddy_series_def": 150, 
            "lead_buddy_series_eva": 124, 
            "lead_buddy_series_hp": 4113, 
            "lead_buddy_series_id": 107001, 
            "lead_buddy_series_matk": 75, 
            "lead_buddy_series_mdef": 142, 
            "lead_buddy_series_mnd": 75, 
            "lead_buddy_series_spd": 130, 
            "lead_buddy_soul_strike_consume_ss_gauge": 1, 
            "lead_buddy_soul_strike_description": "Deliver a lightning-quick sword slash.", 
            "lead_buddy_soul_strike_equipment_image_path": "", 
            "lead_buddy_soul_strike_equipment_series_id": 0, 
            "lead_buddy_soul_strike_id": 20250001, 
            "lead_buddy_soul_strike_image_path": "/dff/static/lang/image/soulstrike/20250001/20250001_256.png", 
            "lead_buddy_soul_strike_name": "Oblivion", 
            "lead_buddy_spd": 130, 
            "lead_buddy_weapon_id": 254114214, 
            "lead_buddy_weapon_image_path": "/dff/static/lang/image/equipment/21003010/21003010_05_112.png", 
            "lead_buddy_weapon_level": 20, 
            "lead_buddy_weapon_max_level": 20, 
            "lead_buddy_weapon_name": "Nodachi (X)\uff0b", 
            "lead_buddy_weapon_series_id": 110001, 
            "nickname": "Sejuani", 
            "profile_message": "summonerino plizerino", 
            "relation_status": 0, 
            "relation_updated_at": 0, 
            "user_id": 4596822181937152, 
            "via_battle": false
        }, 
        {
            "is_new_relation": false, 
            "last_logged_in_at": 1437275439, 
            "lead_buddy_acc": 118, 
            "lead_buddy_accessory_id": 52814015, 
            "lead_buddy_accessory_image_path": "/dff/static/lang/image/equipment/23080001/23080001_01_112.png", 
            "lead_buddy_accessory_level": 1, 
            "lead_buddy_accessory_max_level": 1, 
            "lead_buddy_accessory_name": "Power Wrist (VII)", 
            "lead_buddy_accessory_series_id": 107001, 
            "lead_buddy_armor_id": 159736961, 
            "lead_buddy_armor_image_path": "/dff/static/lang/image/equipment/22053019/22053019_05_112.png", 
            "lead_buddy_armor_level": 20, 
            "lead_buddy_armor_max_level": 20, 
            "lead_buddy_armor_name": "Balamb Garden Uniform (VIII)", 
            "lead_buddy_armor_series_id": 108001, 
            "lead_buddy_atk": 148, 
            "lead_buddy_def": 166, 
            "lead_buddy_eva": 122, 
            "lead_buddy_hp": 2899, 
            "lead_buddy_id": 11000300, 
            "lead_buddy_image_path": "/dff/static/lang/image/buddy/11000300/11000300.png", 
            "lead_buddy_job_name": "Guardian", 
            "lead_buddy_level": 48, 
            "lead_buddy_matk": 69, 
            "lead_buddy_mdef": 171, 
            "lead_buddy_mnd": 75, 
            "lead_buddy_series_acc": 118, 
            "lead_buddy_series_atk": 148, 
            "lead_buddy_series_def": 166, 
            "lead_buddy_series_eva": 122, 
            "lead_buddy_series_hp": 2899, 
            "lead_buddy_series_id": 110001, 
            "lead_buddy_series_matk": 69, 
            "lead_buddy_series_mdef": 171, 
            "lead_buddy_series_mnd": 75, 
            "lead_buddy_series_spd": 119, 
            "lead_buddy_soul_strike_consume_ss_gauge": 1, 
            "lead_buddy_soul_strike_description": "Deal water elemental damage to all targets.", 
            "lead_buddy_soul_strike_equipment_image_path": "", 
            "lead_buddy_soul_strike_equipment_series_id": 0, 
            "lead_buddy_soul_strike_id": 20150001, 
            "lead_buddy_soul_strike_image_path": "/dff/static/lang/image/soulstrike/20150001/20150001_256.png", 
            "lead_buddy_soul_strike_name": "Element Reels", 
            "lead_buddy_spd": 119, 
            "lead_buddy_weapon_id": 76071612, 
            "lead_buddy_weapon_image_path": "/dff/static/lang/image/equipment/21013001/21013001_04_112.png", 
            "lead_buddy_weapon_level": 15, 
            "lead_buddy_weapon_max_level": 15, 
            "lead_buddy_weapon_name": "Moonring Blade (VI)", 
            "lead_buddy_weapon_series_id": 106001, 
            "nickname": "RyuuMage", 
            "profile_message": "Hi All!", 
            "relation_status": 0, 
            "relation_updated_at": 0, 
            "user_id": 4912990105108480, 
            "via_battle": false
        }, 
        {
            "is_new_relation": false, 
            "last_logged_in_at": 1437278127, 
            "lead_buddy_acc": 110, 
            "lead_buddy_accessory_id": 292180615, 
            "lead_buddy_accessory_image_path": "/dff/static/lang/image/equipment/23080001/23080001_01_112.png", 
            "lead_buddy_accessory_level": 1, 
            "lead_buddy_accessory_max_level": 1, 
            "lead_buddy_accessory_name": "Power Wrist (VII)", 
            "lead_buddy_accessory_series_id": 107001, 
            "lead_buddy_armor_id": 330372490, 
            "lead_buddy_armor_image_path": "/dff/static/lang/image/equipment/22052016/22052016_05_112.png", 
            "lead_buddy_armor_level": 13, 
            "lead_buddy_armor_max_level": 20, 
            "lead_buddy_armor_name": "Dark Helm (IV)", 
            "lead_buddy_armor_series_id": 104001, 
            "lead_buddy_atk": 141, 
            "lead_buddy_def": 150, 
            "lead_buddy_eva": 126, 
            "lead_buddy_hp": 3367, 
            "lead_buddy_id": 10400100, 
            "lead_buddy_image_path": "/dff/static/lang/image/buddy/10400100/10400100.png", 
            "lead_buddy_job_name": "Dark Knight", 
            "lead_buddy_level": 36, 
            "lead_buddy_matk": 42, 
            "lead_buddy_mdef": 123, 
            "lead_buddy_mnd": 52, 
            "lead_buddy_series_acc": 111, 
            "lead_buddy_series_atk": 166, 
            "lead_buddy_series_def": 211, 
            "lead_buddy_series_eva": 127, 
            "lead_buddy_series_hp": 4120, 
            "lead_buddy_series_id": 104001, 
            "lead_buddy_series_matk": 53, 
            "lead_buddy_series_mdef": 175, 
            "lead_buddy_series_mnd": 66, 
            "lead_buddy_series_spd": 97, 
            "lead_buddy_soul_strike_consume_ss_gauge": 1, 
            "lead_buddy_soul_strike_description": "Deal physical dark damage to one target.", 
            "lead_buddy_soul_strike_equipment_image_path": "/dff/static/lang/image/equipment/22052016/22052016_05_112.png", 
            "lead_buddy_soul_strike_equipment_series_id": 104001, 
            "lead_buddy_soul_strike_id": 21000012, 
            "lead_buddy_soul_strike_image_path": "/dff/static/lang/image/soulstrike/21000012/21000012_256.png", 
            "lead_buddy_soul_strike_name": "Dark Shot", 
            "lead_buddy_spd": 93, 
            "lead_buddy_weapon_id": 292466512, 
            "lead_buddy_weapon_image_path": "/dff/static/lang/image/equipment/21002045/21002045_04_112.png", 
            "lead_buddy_weapon_level": 15, 
            "lead_buddy_weapon_max_level": 15, 
            "lead_buddy_weapon_name": "Mythril Saber (VII)\uff0b", 
            "lead_buddy_weapon_series_id": 107001, 
            "nickname": "Chowhawk", 
            "profile_message": "It's me! Ryan Rhoads!", 
            "relation_status": 0, 
            "relation_updated_at": 0, 
            "user_id": 4800712093466624, 
            "via_battle": false
        }, 
        {
            "is_new_relation": false, 
            "last_logged_in_at": 1437279624, 
            "lead_buddy_acc": 111, 
            "lead_buddy_accessory_id": 304064284, 
            "lead_buddy_accessory_image_path": "/dff/static/lang/image/equipment/23080001/23080001_01_112.png", 
            "lead_buddy_accessory_level": 1, 
            "lead_buddy_accessory_max_level": 1, 
            "lead_buddy_accessory_name": "Power Wrist (VII)", 
            "lead_buddy_accessory_series_id": 107001, 
            "lead_buddy_armor_id": 309466154, 
            "lead_buddy_armor_image_path": "/dff/static/lang/image/equipment/22054014/22054014_04_112.png", 
            "lead_buddy_armor_level": 15, 
            "lead_buddy_armor_max_level": 15, 
            "lead_buddy_armor_name": "Crystal Armor (V)", 
            "lead_buddy_armor_series_id": 105001, 
            "lead_buddy_atk": 212, 
            "lead_buddy_def": 164, 
            "lead_buddy_eva": 124, 
            "lead_buddy_hp": 3557, 
            "lead_buddy_id": 10700100, 
            "lead_buddy_image_path": "/dff/static/lang/image/buddy/10700100/10700100.png", 
            "lead_buddy_job_name": "SOLDIER", 
            "lead_buddy_level": 48, 
            "lead_buddy_matk": 90, 
            "lead_buddy_mdef": 109, 
            "lead_buddy_mnd": 69, 
            "lead_buddy_series_acc": 111, 
            "lead_buddy_series_atk": 212, 
            "lead_buddy_series_def": 164, 
            "lead_buddy_series_eva": 124, 
            "lead_buddy_series_hp": 3557, 
            "lead_buddy_series_id": 107001, 
            "lead_buddy_series_matk": 90, 
            "lead_buddy_series_mdef": 109, 
            "lead_buddy_series_mnd": 69, 
            "lead_buddy_series_spd": 122, 
            "lead_buddy_soul_strike_consume_ss_gauge": 1, 
            "lead_buddy_soul_strike_description": "Deal three consecutive attacks to random targets.", 
            "lead_buddy_soul_strike_equipment_image_path": "/dff/static/lang/image/equipment/21002061/21002061_05_112.png", 
            "lead_buddy_soul_strike_equipment_series_id": 110001, 
            "lead_buddy_soul_strike_id": 21000008, 
            "lead_buddy_soul_strike_image_path": "/dff/static/lang/image/soulstrike/21000008/21000008_256.png", 
            "lead_buddy_soul_strike_name": "Sonic Buster", 
            "lead_buddy_spd": 122, 
            "lead_buddy_weapon_id": 325602467, 
            "lead_buddy_weapon_image_path": "/dff/static/lang/image/equipment/21002061/21002061_05_112.png", 
            "lead_buddy_weapon_level": 20, 
            "lead_buddy_weapon_max_level": 20, 
            "lead_buddy_weapon_name": "Soldier's Sabre (X)", 
            "lead_buddy_weapon_series_id": 110001, 
            "nickname": "Jupiter", 
            "profile_message": "Hello there!", 
            "relation_status": 0, 
            "relation_updated_at": 0, 
            "user_id": 5988304403038208, 
            "via_battle": false
        }, 
        {
            "is_new_relation": false, 
            "last_logged_in_at": 1437279498, 
            "lead_buddy_acc": 116, 
            "lead_buddy_accessory_id": 292344922, 
            "lead_buddy_accessory_image_path": "/dff/static/lang/image/equipment/23080001/23080001_01_112.png", 
            "lead_buddy_accessory_level": 1, 
            "lead_buddy_accessory_max_level": 1, 
            "lead_buddy_accessory_name": "Power Wrist (VII)", 
            "lead_buddy_accessory_series_id": 107001, 
            "lead_buddy_armor_id": 288295452, 
            "lead_buddy_armor_image_path": "/dff/static/lang/image/equipment/22056017/22056017_05_112.png", 
            "lead_buddy_armor_level": 20, 
            "lead_buddy_armor_max_level": 20, 
            "lead_buddy_armor_name": "Gold Armlet (VII)", 
            "lead_buddy_armor_series_id": 107001, 
            "lead_buddy_atk": 170, 
            "lead_buddy_def": 111, 
            "lead_buddy_eva": 126, 
            "lead_buddy_hp": 1824, 
            "lead_buddy_id": 10000200, 
            "lead_buddy_image_path": "/dff/static/lang/image/buddy/10000200/10000200.png", 
            "lead_buddy_job_name": "Keeper", 
            "lead_buddy_level": 26, 
            "lead_buddy_matk": 62, 
            "lead_buddy_mdef": 116, 
            "lead_buddy_mnd": 57, 
            "lead_buddy_series_acc": 116, 
            "lead_buddy_series_atk": 170, 
            "lead_buddy_series_def": 111, 
            "lead_buddy_series_eva": 126, 
            "lead_buddy_series_hp": 1824, 
            "lead_buddy_series_id": 200001, 
            "lead_buddy_series_matk": 62, 
            "lead_buddy_series_mdef": 116, 
            "lead_buddy_series_mnd": 57, 
            "lead_buddy_series_spd": 93, 
            "lead_buddy_soul_strike_consume_ss_gauge": 1, 
            "lead_buddy_soul_strike_description": "Give the party Protect.", 
            "lead_buddy_soul_strike_equipment_image_path": "/dff/static/lang/image/equipment/22056017/22056017_05_112.png", 
            "lead_buddy_soul_strike_equipment_series_id": 107001, 
            "lead_buddy_soul_strike_id": 21000006, 
            "lead_buddy_soul_strike_image_path": "/dff/static/lang/image/soulstrike/21000006/21000006_256.png", 
            "lead_buddy_soul_strike_name": "Veil of Protection", 
            "lead_buddy_spd": 93, 
            "lead_buddy_weapon_id": 288293927, 
            "lead_buddy_weapon_image_path": "/dff/static/lang/image/equipment/21002042/21002042_05_112.png", 
            "lead_buddy_weapon_level": 19, 
            "lead_buddy_weapon_max_level": 20, 
            "lead_buddy_weapon_name": "Blitz Sword (VIII)", 
            "lead_buddy_weapon_series_id": 108001, 
            "nickname": "Yoo", 
            "profile_message": "Hello there!", 
            "relation_status": 0, 
            "relation_updated_at": 0, 
            "user_id": 5500714683990016, 
            "via_battle": false
        }
    ], 
    "user_relations": [
        {
            "is_new_relation": false, 
            "relation_status": 0, 
            "relation_updated_at": 0, 
            "target_user_id": 4596822181937152, 
            "user_id": 5143210343006208
        }, 
        {
            "is_new_relation": false, 
            "relation_status": 0, 
            "relation_updated_at": 0, 
            "target_user_id": 4912990105108480, 
            "user_id": 5143210343006208
        }, 
        {
            "is_new_relation": false, 
            "relation_status": 0, 
            "relation_updated_at": 0, 
            "target_user_id": 4800712093466624, 
            "user_id": 5143210343006208
        }, 
        {
            "is_new_relation": false, 
            "relation_status": 0, 
            "relation_updated_at": 0, 
            "target_user_id": 5988304403038208, 
            "user_id": 5143210343006208
        }, 
        {
            "is_new_relation": false, 
            "relation_status": 0, 
            "relation_updated_at": 0, 
            "target_user_id": 5500714683990016, 
            "user_id": 5143210343006208
        }
    ]
}
